{"version":"v2","browserEnv":"chrome","editionEnv":"pro","backupType":"local","time":1764693099912,"extVersion":"11.0.19","data":{"site":{"sites":[[{"name":"影视","uuid":"8001e020o3v1sz74hecbdz8otg13b0","updatetime":1580615864289,"id":"8d81fdf8-35dc-4210-92b7-71025d2f02e5","children":[{"name":"哔哩哔哩 (゜-゜)つロ 干杯~-bilibili","uuid":"b475973305c160e23c30539505091916","updatetime":1594029650743,"id":"ed8e11db-12d9-46b9-821b-b384969cc9c1","target":"https://www.bilibili.com/","type":"web","bgImage":"https://infinitypro-img.infinitynewtab.com/custom-icon/9001c91g3utjee9xucs5xfhgi0goag.png","bgType":"image","bgFont":30,"bgText":""},{"bgType":"image","bgImage":"https://infinitypro-img.infinitynewtab.com/custom-icon/icon-1h12asvl2oz3atgi3o68i71mah8.png","target":"https://laplace.live/","name":"明前奶绿 ✽ LAPLACE","uuid":"site-1h12at0tt0kqpkzzn3jkybi60c6","id":"siteId-1h12at0ttcbup6wsll79syjgl3r","type":"web","updatetime":1684779467709},{"bgType":"image","bgImage":"https://infinitypro-img.infinitynewtab.com/custom-icon/icon-1hmjqfvln5b9jx44mp8b0a8xryz.png","target":"https://www.modelscope.cn/profile/xzjosh","name":"ai声音魔搭社区","uuid":"site-1hmjqfvtih7cykd6c08pzwyw4i7","id":"siteId-1hmjqfvtiork61q4te30fyy8949","type":"web","updatetime":1707914821554},{"bgType":"image","bgImage":"https://infinitypro-img.infinitynewtab.com/custom-icon/icon-1japu8psjr56n7f4bu4lw92lrgm.png","target":"https://rdfplayer.mrgaocloud.com/#demo","name":"红狐弹幕播放器-RdfPlayerPro | such a beautiful web player","uuid":"site-1japu8q9no7oujnxn2z16i2hpll","id":"siteId-1japu8q9nh4scyek98hbpcxemvd","type":"web","updatetime":1763954682167},{"name":"netflix","uuid":"6fc09f6b94e8292284cac6c8f386dea8","updatetime":1633498320380,"id":"812342a8-ca41-44e3-80f3-ac2f9ab70d78","target":"https://www.netflix.com/browse#this-is-netflix","type":"web","bgImage":"https://infinitypro-img.infinitynewtab.com/custom-icon/9001cb21obr1ga650mny7q9di21u32.png","bgType":"image","bgFont":30,"bgText":"","bgColor":""},{"name":"完美看看-海量高清电影、电视剧、动漫免费在线观看","uuid":"8001dvtangk9l2o5a4jn2lr8j0ahpf","updatetime":1580458558089,"id":"7017b94f-06e4-4aea-9a92-b811b25725ef","target":"https://www.wanmeikk.me/","type":"web","bgType":"color","bgFont":34,"bgText":"看看","bgColor":"#df5f47"},{"name":"磁力熊 - 豆瓣高分电影1080P高清磁力下载","uuid":"8001e020nm41x64h0t3gzj61ko84l2","updatetime":1580615850113,"id":"ea47454b-38d1-41d5-adc6-71a3b358cbad","target":"https://www.cilixiong.com/","type":"web","bgType":"color","bgFont":27,"bgText":"磁力熊","bgColor":"#6c4cb9"},{"name":"NO – 不负追剧好时光 (￣▽￣)\"","uuid":"8001dppctqqfwgfk1cac0u1eilq1to","updatetime":1573884193615,"id":"cb278a3c-3dd1-492d-9270-8f759bb88f1d","target":"http://www.novipnoad.com/","type":"web","bgType":"color","bgFont":23,"bgText":"NO视频","bgColor":"#6c4cb9"},{"name":"电影蜜蜂-高清电影资源最新电影下载","uuid":"8001e020krfd817qlorwxw8rkd0uf2","updatetime":1580615757293,"id":"ed180217-db6d-4a28-baa9-b70f54f9879b","target":"https://www.dybee.tv/","type":"web","bgType":"color","bgFont":34,"bgText":"电影","bgColor":"#faec63"},{"name":"去看TV_看看屋影视大全_全看网_全视频TV_高清影视剧在线 _ 去看TV","uuid":"8001e020m799dsbebadmvvhd9czdft","updatetime":1612671599474,"id":"961f0926-4729-4261-ba90-e5a85b21b0a8","target":"http://iqukantv.net","type":"web","bgType":"color","bgFont":24,"bgText":"去看TV","bgColor":"#df5f47"},{"name":"1090影视,1090ys.com,1090ys1.com,免费无删减电影,美剧,韩剧,日剧,动漫,国产剧在线看 - 无水印高清在线播放影视网站","uuid":"8001e020n6ano35cpxgn5dwagyjsos","updatetime":1580615833943,"id":"4d06035d-b68d-4c20-95d7-4c3a4bb0801f","target":"http://1090ys.com/","type":"web","bgType":"color","bgFont":18,"bgText":"1090影视","bgColor":"#efa738"},{"name":"电影字幕 - Sub HD","uuid":"8001djdoi5ieb5z8nrtmqf3k1bnftm","updatetime":1584978033418,"id":"e9732643-6ee5-4fa7-9290-64b42c817b70","target":"https://subhd.tv/db0/movie","type":"web","bgType":"color","bgFont":20,"bgText":"电影字幕","bgColor":"#60c0d6"},{"name":"音范丝|影音集|精选4K蓝光原盘下载，顶级收藏","uuid":"8001e0mksiogi2l8hu62nw5u83wgeh","updatetime":1581308070672,"id":"3c1db5dc-1948-4be1-86f6-4a48d8d6987c","target":"http://www.yinfans.me/","type":"web","bgType":"color","bgFont":34,"bgText":"4K","bgColor":"#6c4cb9"},{"bgType":"color","bgColor":"rgba(0,116,255,1)","bgFont":30,"bgText":"片源","bgImage":"","target":"https://pianyuan.org/User/login.html","name":"片源网(pianyuan.org)","bgColorImage":null,"iconType":"color","uuid":"site-1fdr15377v2fv071y7bvagsrcpu","id":"siteId-1fdr15377vz0pvs9tfb8i9mj6ch","type":"web","updatetime":1629773532391},{"bgType":"color","bgColor":"rgba(44,214,223,1)","bgFont":18,"bgText":"天空影视","bgImage":"","target":"https://www.tkys.tv/","name":"天空影视","bgColorImage":null,"iconType":"color","uuid":"site-1fhpodu4amzd4f3ut8zytgtvzut","id":"siteId-1fhpodu4a6tnzdhtxy71os6t6yw","type":"web","updatetime":1634025797770},{"bgType":"color","bgColor":"rgba(255,71,52,1)","bgFont":30,"bgText":"低端","target":"https://ddys.info/","name":"低端影视发布页","bgColorImage":null,"uuid":"site-1ic86jsvr7dh02kbab3betg83ek","id":"siteId-1ic86jsvr5bngusb68kzmbhh6cb","type":"web","updatetime":1731147199483},{"name":"豆瓣电影","uuid":"e7c4be9acaa79d546104fe5b2fcd69fa","bgType":"image","bgImage":"https://infinitypro-img.infinitynewtab.com/custom-icon/9001c1kkipde7heoc7ritueg8rihhw.png","updatetime":1636453434758,"id":"siteId-1fk23jhc61z4t4m6m7uzuh8limj","target":"http://movie.douban.com/","type":"web"},{"bgType":"color","bgColor":"rgba(255,71,52,1)","bgFont":30,"bgText":"字幕","bgImage":"","target":"https://subhd.tv/","name":"分享交流下载字幕平台 - SubHD","bgColorImage":null,"iconType":"color","uuid":"site-1g1ddrn78iryakycq9c548gveyf","id":"siteId-1g1ddrn78pwlfmltx2tl7uvjq2j","type":"web","updatetime":1650791931112},{"bgType":"image","bgImage":"https://infinitypro-img.infinitynewtab.com/custom-icon/icon-1gujd1f8rof09rjbg4fsna1t8fx.png","target":"https://www.mini4k.com/","name":"最好的高清2160P 4K电影下载网站 | MINI4K迷客电影","uuid":"site-1gujd1fsh53g9ufpq8g8t0tgmrr","id":"siteId-1gujd1fsh9ccma6pt43xt0f2lf5","type":"web","updatetime":1682130911121},{"bgType":"color","bgColor":"rgba(44,214,223,1)","bgFont":30,"bgText":"低端","target":"https://ddys.tv/","name":"低端影视 - 超清在线视频站","bgColorImage":null,"uuid":"site-1gdgcklb34vaz3kyqnigpybx2vc","id":"siteId-1gdgcklb3xkkvv7dhmjzolt1nqu","type":"web","updatetime":1663776216419},{"uuid":"site-1gdhovscqagyu9pw3w147q3v4s6","id":"siteId-1gdhovscq0p0aa9v9xoto0akb7w","type":"web","bgType":"color","bgColor":"rgba(0,116,255,1)","bgFont":30,"bgText":"低端","target":"http://ddys2.me","name":"低端影视 - 超清在线视频站","bgColorImage":null,"updatetime":1663822721433},{"bgType":"image","bgColor":"rgba(52,255,60,0.38)","bgImage":"https://infinitypro-img.infinitynewtab.com/custom-icon/icon-1ginek4ekpmg98nkdo83xtu80hs.png","target":"https://jubt.fun/cn/index.html","name":"聚BT - 聚合最优质的BT、磁力资源 | BT搜索 磁力搜索 云盘搜索 影视APP 在线影视 磁力影视 种子搜索","uuid":"site-1gikese38mc93db5azyvymeb5ga","id":"siteId-1gikese38drar78snj5a70u8h1j","type":"web","updatetime":1669381886817},{"bgType":"image","bgImage":"https://infinitypro-img.infinitynewtab.com/custom-icon/icon-1gineebihoglcrsnmk9xvqh31ka.png","target":"https://www.dlsite.com/index.html","name":"DLsite:从同人志，同人游戏开始，到PC软件，漫画的二次元综合下载商店 | DLsite综合首页","uuid":"site-1gineec8rfyqxb8c6pdaywpz04u","id":"siteId-1gineec8rg1jk1z6lxjqnz8olc1","type":"web","updatetime":1669381697819},{"bgType":"image","bgImage":"https://infinitypro-img.infinitynewtab.com/custom-icon/icon-1gufbrho6rp5cql9639sk0pqw88.png","target":"https://sehuatang.net/","name":"长风渡-小说网","uuid":"site-1gufbri39q16x53u704uemoq6k7","id":"siteId-1gufbri39ilh2u7l1yoxshdp2x2","type":"web","updatetime":1689765819462},{"bgType":"color","bgColor":"rgba(0,116,255,1)","bgFont":17,"bgText":"阿里","bgImage":"","target":"https://pan666.net/","name":"阿里小站","bgColorImage":null,"iconType":"color","uuid":"site-1fcs3i165e15m2017s7sohogm7q","id":"siteId-1fcs3i165fzp0s0fcojmb55mtxh","type":"web","updatetime":1685727650807},{"bgType":"image","bgImage":"https://infinitypro-img.infinitynewtab.com/custom-icon/icon-1g6ev6rgjmdhwh4pu11ds4xi2cd.png","target":"http://yunpanziyuan.xyz","name":"云盘资源网","uuid":"site-1g6ev6rn5p9boxq2k2m6ghd287x","id":"siteId-1g6ev6rn5n3k98vo3pmiu5513b1","type":"web","updatetime":1691467665891,"bgColor":""},{"bgType":"image","bgImage":"https://infinitypro-img.infinitynewtab.com/custom-icon/icon-1h79l7gpp3u0ir5q4nho9at23a9.png","target":"https://docs.qq.com/doc/DTVhJR1RibVNEUmJB","name":"云盘资源网发布页","uuid":"site-1h79l7h55340rgpyqm0d3zqcepf","id":"siteId-1h79l7h556cdqhvjuoc9cgxldsj","type":"web","updatetime":1691467629733}]},{"name":"文件夹","uuid":"8001echp8jg0fne1m8ueox4n1n5h3s","updatetime":1594029788672,"id":"500215a8-7bb8-4921-aa6b-86fe0487e298","children":[{"name":"YouTube","uuid":"d7a733ba6cf6757e5ca4ae92b0bf6842","updatetime":1594029658400,"id":"fd5b2d24-ccd5-484d-bcf6-cf858c53a524","target":"https://www.youtube.com/","type":"web","bgImage":"https://infinityicon.infinitynewtab.com/user-share-icon/d7a733ba6cf6757e5ca4ae92b0bf6842.png","bgType":"image","bgFont":30,"bgText":""},{"name":"Google Voice","uuid":"8ce1dc61021d19f67e48f4a422dfce74","updatetime":1594995554134,"id":"005b0684-d39c-4226-83a7-dc2b94d93621","target":"https://voice.google.com/u/0/messages","type":"web","bgImage":"https://infinitypro-img.infinitynewtab.com/custom-icon/8001e8h1o45fnv8piuk2igul5ppdj5.png","bgType":"image","bgFont":30,"bgText":""},{"name":"Gmail","uuid":"3dad5f9a1281a2ea8b610daef0ed2eac","updatetime":1595034727039,"id":"923425de-d2c0-4174-8b0b-c064f4d451a4","target":"https://mail.google.com/mail/u/0/#inbox","type":"web","bgImage":"https://infinityicon.infinitynewtab.com/user-share-icon/3dad5f9a1281a2ea8b610daef0ed2eac.png","bgType":"image","bgFont":30,"bgText":""},{"bgType":"image","bgImage":"https://infinitypro-img.infinitynewtab.com/custom-icon/icon-1hcurfnv7cyo78dtki28vn6mb4j.png","target":"https://work.weixin.qq.com/mail/","name":"腾讯企业邮箱","uuid":"site-1hcurfo6efo6x4gf9g2c9wrg0im","id":"siteId-1hcurfo6ewyu1ddx5lpqo1qtbjj","type":"web","updatetime":1697547542734},{"name":"Outlook邮箱","uuid":"8ed542d694e597fe32bd74394549d2f6","updatetime":1594031294779,"id":"c09f195a-736b-40b9-a61d-b9ef3ec3be0d","target":"http://www.outlook.com","type":"web","bgImage":"https://infinitypro-img.infinitynewtab.com/custom-icon/9001cbvtqbndd88ca6w3gke2xtfcdy.png","bgType":"image","bgFont":30,"bgText":""},{"name":"ProtonMail","uuid":"5d2f3e9c54b2dcf6f20a37306a372f66","bgType":"image","bgImage":"https://infinitypro-img.infinitynewtab.com/custom-icon/8001dtd68q5g4bnji51skhv32xvufg.png","updatetime":1623415274729,"id":"siteId-1f7thef7azbim89cuqexuj9e5q3","type":"web","target":"http://mail.protonmail.com"},{"name":"Instagram","uuid":"7217a2ae99c3fd510f2f25c4c4866065","updatetime":1594029660327,"id":"a9366148-ccb5-4c6f-b3dc-96c05c9bf3c1","target":"http://www.instagram.com","type":"web","bgImage":"https://infinityicon.infinitynewtab.com/user-share-icon/7217a2ae99c3fd510f2f25c4c4866065.png","bgType":"image","bgFont":30,"bgText":""},{"name":"Facebook","uuid":"92ed240c60c284adc2f2e411205176dc","updatetime":1594996171895,"id":"6bad82cc-a0ee-4ba2-8617-fb3b2e3243f2","target":"https://www.facebook.com","type":"web","bgImage":"https://infinityicon.infinitynewtab.com/user-share-icon/4277652ad8ce6b2d8377b092ad31507c.png","bgType":"image","bgFont":30,"bgText":""},{"name":"pixiv","uuid":"334c5fef299f3120a2bad3b313a71c77","updatetime":1594030488068,"id":"8992cbe7-a489-443a-9aaf-307c8218b852","target":"http://www.pixiv.net/","type":"web","bgImage":"https://infinityicon.infinitynewtab.com/user-share-icon/334c5fef299f3120a2bad3b313a71c77.png","bgType":"image","bgFont":30,"bgText":""},{"name":"Twitch","uuid":"cc90a2d4f1c32709a1fd27061cce66ae","updatetime":1594029851629,"id":"95b48eb0-f486-43c8-b426-e77bfa9405c6","target":"http://www.twitch.tv/directory/all","type":"web","bgImage":"https://infinitypro-img.infinitynewtab.com/custom-icon/9001c260mr2s22tutko2bqplgucqps.png","bgType":"image","bgFont":30,"bgText":""},{"name":"Twitter","uuid":"66117abb3659ad746baadc8c1e0b28df","updatetime":1594029837108,"id":"ac8d3da0-8dcd-4472-ba42-79a8adba5ca0","target":"https://www.twitter.com","type":"web","bgImage":"https://infinityicon.infinitynewtab.com/user-share-icon/8f03e3943a4b730e328bb1d1906e5856.png","bgType":"image","bgFont":30,"bgText":""},{"name":"GroupMe","uuid":"fbe4487694c9f8d7fe842516abc6a414","updatetime":1595036095646,"id":"3042ddb2-6eaa-4ac5-a9a8-3df4079cbc8c","target":"https://web.groupme.com/chats","type":"web","bgImage":"https://infinitypro-img.infinitynewtab.com/custom-icon/9001c5jdu5bm3t8ankubkb8ir8zdw9.png","bgType":"image","bgFont":30,"bgText":""},{"name":"GitHub","uuid":"a23b4cf17327527ae66aad5d13f059da","updatetime":1594029628525,"id":"b2b9b00b-f148-4405-b45d-33158370e4ea","target":"https://github.com/","type":"web","bgImage":"https://infinityicon.infinitynewtab.com/user-share-icon/a23b4cf17327527ae66aad5d13f059da.png","bgType":"image","bgFont":30,"bgText":""},{"name":"谷歌地球","uuid":"24775d443c31420eb976327718f81b7b","updatetime":1594030843327,"id":"4460e0f0-6496-4406-a8f6-65512a1b0ac1","target":"https://www.google.com/earth/","type":"web","bgImage":"https://infinityicon.infinitynewtab.com/user-share-icon/24775d443c31420eb976327718f81b7b.png","bgType":"image","bgFont":30,"bgText":""},{"name":"163邮箱","uuid":"719c3c5c8980d853ae337c42fe0326a8","bgType":"image","bgImage":"https://infinityicon.infinitynewtab.com/user-share-icon/e783a83edc8c4f2c1d96a8dec0a32870.png","updatetime":1627143372610,"id":"siteId-1fbckqvq2ogw2jtn0lpfg8bh90y","target":"http://mail.163.com/","type":"web"},{"name":"","uuid":"c26e03fd46bb5c65fff8f1bf5d1ebc54","bgType":"image","bgImage":"https://infinitypro-img.infinitynewtab.com/custom-icon/8001d6pe6u6e0576lkkvqhea72e5ph.png","updatetime":1687886856119,"id":"siteId-1h3uua7vbduaco0nnhw1lotgrfw","target":"http://pronhub.com","type":"web","bgColor":""},{"name":"Spotify","uuid":"39abee39adadf3a4fab126bd4fec0bec","bgType":"image","bgImage":"https://infinitypro-img.infinitynewtab.com/custom-icon/8001drfvh2gntzkwpqgcjg9x8xw7lj.png","updatetime":1700550535159,"id":"siteId-1hfobbpvobqwpy0bm2e2yczxum3","target":"https://sovrn.co/19egzal","type":"web"},{"name":"腾讯企业邮箱","uuid":"ee99802245a1be3e65fd844cc3183c80","bgType":"image","bgImage":"https://infinityicon.infinitynewtab.com/user-share-icon/ee99802245a1be3e65fd844cc3183c80.png","updatetime":1708678564401,"id":"siteId-1hnairihhbl028yvg31gi5avp51","target":"https://exmail.qq.com","type":"web"}]},{"name":"机场","uuid":"8001e439sknkee3oxqlm6ssh1yv6r6","updatetime":1584953971444,"id":"006ee13e-27a5-4e22-b22b-50bf7438995b","children":[{"name":"RenzheCloud 忍者云","uuid":"8001e7rl1fmgfmel54vfeoph6x5llw","updatetime":1730623079206,"id":"68107db2-83d6-4334-84ea-9f3e5e0a5cc4","target":"https://renzhe.cloud/","type":"web","bgType":"color","bgFont":25,"bgText":"Re","bgColor":"#57a0ee","bgColorImage":null},{"uuid":"site-1gicv8ncinyliii0px01vx7r54m","id":"siteId-1gicv8nci6fp3cgmcopdkzmp3lc","type":"web","bgType":"color","bgColor":"rgba(255,71,52,1)","bgFont":30,"bgText":"火星","target":"https://a.hxlm.cc/","name":"火星联盟_地址发布页","bgColorImage":null,"updatetime":1722576843276},{"bgType":"color","bgColor":"rgba(255,71,52,1)","bgFont":30,"bgText":"奶茶","target":"https://a.naichacloud.net/","name":"奶茶云_地址发布页","bgColorImage":null,"uuid":"site-1h0ouo8u2rpkkqfdswujp0l43uw","id":"siteId-1h0ouo8u2s4m46ewxqe53kub4pm","type":"web","updatetime":1730623225543},{"bgType":"color","bgColor":"rgba(255,71,52,1)","bgFont":30,"bgText":"No","target":"https://peasoft.github.io/NWalls.html","name":"NoMoreWalls - Pea Soft 博客","bgColorImage":null,"uuid":"site-1i48uvd80t49k9v2auwug8j9ujk","id":"siteId-1i48uvd80mxzfq8gwiyhrb0gfj0","type":"web","updatetime":1722582807808},{"bgType":"color","bgColor":"rgba(255,71,52,1)","bgFont":30,"bgText":"斗罗云","target":"https://me.douluoy.store/user#","name":"斗罗云","bgColorImage":null,"uuid":"site-1i48vd97etp43pek3vvxy3qtgvx","id":"siteId-1i48vd97eeu94hhg3kpd7kb2vss","type":"web","updatetime":1722583262446},{"bgType":"color","bgColor":"rgba(255,71,52,1)","bgFont":30,"bgText":"奶茶","target":"https://cf.ieplcloud.net/","name":"奶茶Cloud","bgColorImage":null,"uuid":"site-1ibolbdkou4z2fiz8sf5i62tdls","id":"siteId-1ibolbdkppbq2xf6datgalymv7i","type":"web","updatetime":1730625787141},{"bgType":"image","bgImage":"https://infinitypro-img.infinitynewtab.com/custom-icon/icon-1j01nvpf3vu4uckxbo515fu315a.png","target":"https://xn--9kqz23b19z.com/#/dashboard","name":"仪表盘 - 良心云","uuid":"site-1j01nvpt79juz7gfbi77l5qdyr8","id":"siteId-1j01nvpt7vr9lx89pbqu7fstgxl","type":"web","updatetime":1752405370791},{"bgType":"image","bgImage":"https://infinitypro-img.infinitynewtab.com/custom-icon/icon-1irkhe0bio34fv06vcl5lfxn9ha.png","target":"https://llgjc1.com/#/dashboard","name":"仪表盘 - 流量光机场","uuid":"site-1irkhe0u72bkcns8slszjy7swn3","id":"siteId-1irkhe0u7ymbnb9l3jqb1ncyxbm","type":"web","updatetime":1747667321799},{"bgType":"color","bgColor":"rgba(255,71,52,1)","bgFont":30,"bgText":"赔钱","target":"https://xn--mes358aby2apfg.com/login/","name":"赔钱机场 - 超便宜低价高速机场","bgColorImage":null,"uuid":"site-1j2hkq2ucseca5d3puuw3do5nj4","id":"siteId-1j2hkq2uc2wr5u25iuu3jdzfuqi","type":"web","updatetime":1755086392268}]},{"name":"有用","uuid":"8001dhbte3v4vd2w1qqg64a42xnb2s","updatetime":1564841807844,"id":"f80f1dd1-dd1a-4dbf-a448-887d7e84c1fa","children":[{"uuid":"site-1hs520nn8cgj60hjeuyrxexls5y","id":"siteId-1hs520nn8ut0zibwcpdsdaj7vo2","type":"web","bgType":"image","bgImage":"https://infinitypro-img.infinitynewtab.com/custom-icon/icon-1hs520ng65rla9le9gnkezfg3xc.png","target":"127.0.0.1:5244","name":"AList","updatetime":1713862315713,"bgColor":""},{"bgType":"image","bgImage":"https://infinitypro-img.infinitynewtab.com/custom-icon/icon-1i6rf6prk47723gp7clbfob9u31.png","target":"https://test.ustc.edu.cn/","name":"中科大测速网站","uuid":"site-1i6rf6q678vl5rlfdy7em11i4zb","id":"siteId-1i6rf6q679ow0v03bmrqrv28ot7","type":"web","updatetime":1725351328841,"bgColor":""},{"name":"115网盘","uuid":"c9f05bf83ff9f2217595c20418c1167f","bgType":"image","bgImage":"https://infinityicon.infinitynewtab.com/icon/150330092618.png","updatetime":1672683183777,"id":"siteId-1glpqvnl187jc0yb8zyt6e852ia","target":"http://www.115.com/","type":"web"},{"name":"百度网盘","uuid":"8061c93a71355024e801820969e2ecff","bgType":"image","bgImage":"https://infinityicon.infinitynewtab.com/user-share-icon/8061c93a71355024e801820969e2ecff.png","updatetime":1689509822687,"id":"siteId-1h5fa406vp6uoyrkwi1oelykvj9","target":"http://pan.baidu.com/disk/home#from=share_pan_logo","type":"web"},{"name":"油猴脚本","uuid":"51ac1b5b07141efc426caafcf3a7e78a","updatetime":1594029645503,"id":"3e1b6405-c55e-493b-8142-5d91e6397ee7","target":"https://greasyfork.org/zh-CN/scripts","type":"web","bgImage":"https://infinityicon.infinitynewtab.com/user-share-icon/51ac1b5b07141efc426caafcf3a7e78a.png","bgType":"image","bgFont":30,"bgText":""},{"bgType":"color","bgColor":"rgba(44,214,223,1)","bgFont":27,"bgText":"PikPak","bgImage":"","target":"https://mumuchenchen.github.io/pikpak/#/login","name":"PikPak网盘","bgColorImage":null,"iconType":"color","uuid":"site-1fmrtu27ci942e4vczs5m2qvpqd","id":"siteId-1fmrtu27chzoz8jghd22b3ixt82","type":"web","updatetime":1639467387116},{"name":"钛盘","uuid":"30c8fca32ff49e325735ded5289fabc8","bgType":"image","bgImage":"https://infinitypro-img.infinitynewtab.com/custom-icon/8001eorkk4surcoisqocs1mq6ru28r.png","updatetime":1628518519382,"id":"siteId-1fclk94imzx1rw882h098uhqj15","target":"https://app.tmp.link/?tmpui_page=/","type":"web"},{"bgType":"image","bgImage":"https://infinitypro-img.infinitynewtab.com/custom-icon/icon-1ikh4ro23i0d27nt0kvq0zzvpza.png","target":"https://www.zoomeye.org/","name":"ZoomEye(\"钟馗之眼\")网络空间搜索引擎","uuid":"site-1ikh4rohdzkjlhhiispqphf92q7","id":"siteId-1ikh4rohdae4n7mw5tnw1waalz9","type":"web","updatetime":1740037297891,"bgColor":""},{"name":"天翼云盘","uuid":"1f3b6bc9d294626d1cb952e463855e33","bgType":"image","bgImage":"https://infinitypro-img.infinitynewtab.com/custom-icon/8001ecmgaud32zmals3fxfnv04lozs.png","updatetime":1624259176584,"id":"siteId-1f8mm8a493isy2vwfak88a56kjk","type":"web","target":"https://cloud.189.cn/main.action#security/folder/81301310433751218"},{"bgType":"image","bgImage":"https://infinitypro-img.infinitynewtab.com/custom-icon/icon-1j9lnsavpvkq8surz1drxkg3v0b.png","target":"https://store.rg-adguard.net/","name":"Microsoft Store - Generation Project (v1.2.3) [by @rgadguard & mkuba50]","uuid":"site-1j9lnsbbmoos1vlj3q0nnaukf7q","id":"siteId-1j9lnsbbmrgx4areymiewp3krea","type":"web","updatetime":1762740022646},{"name":"白描网页版","uuid":"39eac3eeff8ad3dca56ecc54044ed4b8","bgType":"image","bgImage":"https://infinitypro-img.infinitynewtab.com/custom-icon/8001e9b2rqd2kbd1v9xgj57wypnjyf.png","updatetime":1628780423040,"id":"siteId-1fcte1ps0cgnri0795vr98t2ii0","target":"https://web.baimiaoapp.com/","type":"web"},{"bgType":"color","bgColor":"rgba(255,71,52,1)","bgFont":30,"bgText":"软仓","target":"https://www.ruancang.net/","name":"软仓 | RuanCang.Net","bgColorImage":null,"uuid":"site-1j4qtrgtj9k82ldw93bvouys23l","id":"siteId-1j4qtrgtkz41ct68lya69ap4yvw","type":"web","updatetime":1757545350068},{"name":"MSDN, 我告诉你","uuid":"b66731190ac31c4a3ae643832e322238","updatetime":1594030727701,"id":"42a1f845-0856-411d-855c-a5358213fdf1","target":"https://msdn.itellyou.cn/","type":"web","bgImage":"https://infinitypro-img.infinitynewtab.com/custom-icon/9001cc1eclasqslytacj7p91hius26.png","bgType":"image","bgFont":30,"bgText":""},{"name":"胡萝卜周","uuid":"8001eestjpvfhkicn4rqmbg7tqey0a","updatetime":1596550932461,"id":"c98ff782-956b-48f9-8281-177d802244a9","target":"https://www.carrotchou.com/","type":"web","bgImage":"https://infinitypro-img.infinitynewtab.com/custom-icon/9001chhk1q0j7urksp4kg5eva8uldt.png","bgType":"image","bgFont":30,"bgText":""},{"bgType":"image","bgImage":"https://infinitypro-img.infinitynewtab.com/custom-icon/icon-1hp0a6s9nktcp98vsx4n140lm4e.png","target":"https://adzhp.xyz/","name":"爱达杂货铺 | 收集那些有用的东西|爱达导航","uuid":"site-1hp0a6t13xq4sk7bw69uc24ek0g","id":"siteId-1hp0a6t13ia52luddyfglyy74xh","type":"web","updatetime":1710481437731},{"bgType":"image","bgImage":"https://infinitypro-img.infinitynewtab.com/custom-icon/icon-1j6ehq35nbz25gv3y1nd9ygfl93.png","target":"https://www.bestvideow.com/","name":"免费视频解析下载_抖音，B站(哔哩哔哩)视频解析下载工具 - Best Video下载器","uuid":"site-1j6ehq4eij6q7rsektd2g602xbp","id":"siteId-1j6ehq4ei7ynqbhgru0h2nubyr0","type":"web","updatetime":1759277552082},{"bgType":"color","bgColor":"rgba(255,71,52,1)","bgFont":30,"bgText":"资源","target":"https://www.ahhhhfs.com/welfare/","name":"资源 | ahhhhfs","bgColorImage":null,"uuid":"site-1hnlit6lq4qjn3jiety50f7055v","id":"siteId-1hnlit6lqfqeyemvhb3bo9gwj2z","type":"web","updatetime":1709047716538},{"name":"落尘之木","uuid":"4b0de6b1231ccdec3080de6086571d0b","updatetime":1594031252403,"id":"1832caba-6a81-4d4b-8919-b64a60a8514e","target":"https://www.luochenzhimu.com/","type":"web","bgImage":"https://infinitypro-img.infinitynewtab.com/custom-icon/8001cs6ri796vg0nywurbdoj3pieix.png","bgType":"image","bgFont":30,"bgText":""},{"bgType":"image","bgImage":"https://infinitypro-img.infinitynewtab.com/custom-icon/icon-1i16m8flh6j1h2lfnxqgacrz9a7.png","target":"https://vcb-s.com/archives/16609","name":"基于 MPC-HC 和 madVR 的播放器配置入门 | VCB-Studio","uuid":"site-1i16m8g7g8o17a66937yyf1faec","id":"siteId-1i16m8g7gabn40d9n74uhqe237m","type":"web","updatetime":1719285334256},{"name":"OfficePLUS，微软Office官方在线模板网站！","uuid":"8001ecia3je1qad1qacwtr3xbc54ko","updatetime":1594047450559,"id":"3bf608a6-8681-402c-b421-d00a92597054","target":"http://www.officeplus.cn/Template/Home.shtml","type":"web","bgImage":"https://infinitypro-img.infinitynewtab.com/custom-icon/9001c8rlnrluju2en5gdhqvixfhiu6.png","bgType":"image","bgFont":30,"bgText":""},{"name":"423Down","uuid":"66aecd81f9d6f67113a4b53898e66330","bgType":"image","bgImage":"https://infinitypro-img.infinitynewtab.com/custom-icon/9001cigmb8m6ppb3z8rzincoer8y2p.png","updatetime":1627564508959,"id":"siteId-1fbp6f1p0nnfurwjs56rzq6wyyf","target":"http://www.423down.com/","type":"web"},{"name":"封面提取_bilibili封面提取_av号封面提取","uuid":"8001dm3p03s4w1l8bsmayjrnaofaui","updatetime":1569937428356,"id":"63695436-d45d-4ac2-a975-724156c7c2fb","target":"http://www.galmoe.com/","type":"web","bgType":"color","bgFont":34,"bgText":"封面","bgColor":"#6c4cb9"},{"bgType":"image","bgImage":"https://infinitypro-img.infinitynewtab.com/custom-icon/icon-1hnlivrtoougwl2w7w6bqgkj5e9.png","target":"https://zyscj.com/","name":"资源收藏夹","uuid":"site-1hnlivsaricqwx05x2e6afl1feh","id":"siteId-1hnlivsar4bwqikw1yk02vkt4or","type":"web","updatetime":1709047804251},{"bgType":"color","bgColor":"rgba(0,116,255,1)","bgFont":21,"bgText":"123云盘","bgImage":"","target":"https://www.123pan.com/","name":"123云盘","bgColorImage":null,"iconType":"color","uuid":"site-1fjq4md2dx0ylimq1wb96x90ksj","id":"siteId-1fjq4md2ddgi8bf2f3iksyhhsnk","type":"web","updatetime":1636186141773},{"name":"鸠摩搜索 - 文档搜索引擎","uuid":"8001dolkfp419lgdv4nm6rzct32mti","updatetime":1572684162177,"id":"d06413f2-cb26-4348-ac73-8cb14bc9590a","target":"https://www.jiumodiary.com/","type":"web","bgType":"color","bgFont":34,"bgText":"鸠摩","bgColor":"#6c4cb9"},{"bgType":"image","bgImage":"https://infinitypro-img.infinitynewtab.com/custom-icon/icon-1hpv3mbj8cey5ky7xqi2q0zusr5.png","target":"https://flingtrainer.com/","name":"FLiNG Trainer - PC Game Cheats and Mods","uuid":"site-1hpv3mc54tsyvjb0l6nsjrvnkek","id":"siteId-1hpv3mc54tbewzpijfuweqxugxy","type":"web","updatetime":1711514792100},{"name":"秘迹搜索","uuid":"8001drg58q73pj0y6zm2dw1tqn0y8d","updatetime":1575721658596,"id":"e97082ce-2000-4039-8837-65d624b4e468","target":"https://mijisou.com/","type":"web","bgType":"color","bgFont":34,"bgText":"秘迹","bgColor":"#60c0d6"},{"name":"独特工具箱：免费的在线工具网站 - dute.org","uuid":"8001euivpnj92jx6rxqr4iruzyzz15","updatetime":1613397548649,"id":"e34e1d9c-f4fb-4d2e-8038-5ae9714a062b","target":"https://www.dute.org/","type":"web","bgType":"color","bgFont":15,"bgText":"独特工具箱","bgColor":"transparent"},{"name":"AE","uuid":"8001dhahea7uk8giaq64efrta9b7jo","updatetime":1584977706682,"id":"a06801d8-e6b1-427a-adf9-dae2d8ce1af8","target":"http://www.lookae.com/","type":"web","bgType":"color","bgFont":24,"bgText":"lookAE","bgColor":"#efa738"},{"name":"MikuTools - 一个轻量的工具集合","uuid":"8001e2l20bltw6n01b6genl8o5qbtl","updatetime":1583402200765,"id":"6baaed9c-e040-4422-bde0-a485caf60b62","target":"https://tools.miku.ac/","type":"web","bgType":"color","bgFont":21,"bgText":"工具集合","bgColor":"#57a0ee"},{"name":"免费接短信,在线接收短信验证码 - 云短信","uuid":"8001e3ln4stjzyzqk5vmr77zp3qas5","updatetime":1584498111411,"id":"53d2bf7e-9276-4acf-844c-78f8ee3ff967","target":"https://yunduanxin.net/","type":"web","bgType":"color","bgFont":17,"bgText":"临时手机","bgColor":"#efa738"},{"name":"360查字体-查版权，免纠纷","uuid":"8001e2urud2ki28lx1co6b1hycg3bj","updatetime":1583731389524,"id":"8dfd2229-2214-4608-b3ad-5f1d9d8c7bcb","target":"http://fonts.safe.360.cn/","type":"web","bgType":"color","bgFont":26,"bgText":"查字体","bgColor":"#73b364"},{"bgType":"color","bgColor":"rgba(44,214,223,1)","bgFont":17,"bgText":"KinhDown","bgImage":"","target":"https://kinhdown.kinh.cc/","name":"KinhDown（加速！永无止境）","bgColorImage":"https://infinitypro-img.infinitynewtab.com/custom-icon/icon-1f84iaqhsb9p568w8q3j2c4zv30.png","iconType":"color","uuid":"site-1f84iaqpg87sj8vvd6jgslaiuee","id":"siteId-1f84iaqpgpzbea0p8txmgdmvrma","type":"web","updatetime":1623651085104},{"bgType":"color","bgColor":"rgba(255,207,12,1)","bgFont":30,"bgText":"聚BT","bgImage":"","target":"https://jubt.ml/cn/index.html","name":"聚BT - 聚合最优质的BT、磁力资源 | BT搜索 磁力搜索 云盘搜索 影视APP 在线影视 磁力影视 种子搜索","bgColorImage":null,"iconType":"color","uuid":"site-1fcs1e7jr1p3j5f60yv9xctxu4p","id":"siteId-1fcs1e7jr8s8f0h83wcxnu8wgky","type":"web","updatetime":1628733644411},{"name":"文叔叔","uuid":"2ba621a24772050f1637a1c338c1ae03","bgType":"image","bgImage":"https://infinitypro-img.infinitynewtab.com/custom-icon/8001eaudsedq8bkb3yk040gv97bw99.png","updatetime":1652951805118,"id":"siteId-1g3dplr5vnw7gz73p8thfnfuv70","target":"https://www.wenshushu.cn/","type":"web"},{"name":"蓝奏云","uuid":"fef41b1582ea843cb21c40b039ae48ed","bgType":"image","bgImage":"https://infinitypro-img.infinitynewtab.com/custom-icon/8001d7qsf3020c3dm9g3brcl81xlm4.png","updatetime":1652951828560,"id":"siteId-1g3dpmi2gtn0bqeqrk763kgg3pp","target":"https://www.lanzou.com/u","type":"web"},{"bgType":"image","bgImage":"https://infinitypro-img.infinitynewtab.com/custom-icon/icon-1gkpsapj8js4q9rqk519kt33g5f.png","target":"http://hi.pcmoe.net/Buddha.html","name":"新约佛论禅/佛曰加密 - PcMoe!","uuid":"site-1gkpsaq5eadu4xzo79rvsf5fvkp","id":"siteId-1gkpsaq5elogghqao6d70zgnx28","type":"web","updatetime":1671610853550},{"bgType":"image","bgImage":"https://infinitypro-img.infinitynewtab.com/custom-icon/icon-1gkqon2moqjj9mr4tb120lajoj4.png","target":"http://idea.955code.com/","name":"IDEA激活码,idea最新永久激活码,idea破解,pycharm激活码,pycharm永久激活码","uuid":"site-1gkqon3a4k6pkv7jiay44vp7iez","id":"siteId-1gkqon3a4tiowfifjqx2fi7wl1f","type":"web","updatetime":1671640616260},{"bgType":"image","bgImage":"https://infinitypro-img.infinitynewtab.com/custom-icon/icon-1h60s5kf7kz33hssuehk02uta50.png","target":"https://www.watermarkremover.io/zh","name":"水印去除剂 - 删除照片中的任何水印","uuid":"site-1h60s5ktotcb9i7rtdpylvpav18","id":"siteId-1h60s5ktoyu86wmsunc6iqjwa16","type":"web","updatetime":1690099176376},{"bgType":"image","bgImage":"https://infinitypro-img.infinitynewtab.com/custom-icon/icon-1hfou3v56rw3b8855ohabj0i0v8.png","target":"https://www.runningcheese.com/","name":"奔跑中的奶酪","uuid":"site-1hfou3vh1449sxthr89azb1x2oe","id":"siteId-1hfou3vh14r77j70ophlroenk3i","type":"web","updatetime":1700570201633},{"bgType":"image","bgImage":"https://infinitypro-img.infinitynewtab.com/custom-icon/icon-1hefo2i4ekwi4692lfr7bqhtaun.png","target":"https://cook.yunyoujun.cn/?continueFlag=4892de72dccce80188d1048025a8a114","name":"食用手册","uuid":"site-1hefo2kmrslymn8k5w6qazvtvx3","id":"siteId-1hefo2kmrbffvsgyt7o08wilyys","type":"web","updatetime":1699188134619},{"bgType":"image","bgImage":"https://infinitypro-img.infinitynewtab.com/custom-icon/icon-1hq9f8p0qsmlgvomddxji3731fj.png","target":"https://store.rg-adguard.net/","name":"Microsoft Store - Generation Project (v1.2.3) [by @rgadguard & mkuba50]","uuid":"site-1hq9f8pg4hyovubbyhv9b3p2b1u","id":"siteId-1hq9f8pg49j1qzn4rwdh2ixv5do","type":"web","updatetime":1711862474244},{"bgType":"image","bgImage":"https://infinitypro-img.infinitynewtab.com/custom-icon/icon-1hnujt47847inwitcacm17qtdns.png","target":"https://www.linshiyouxiang.net/","name":"临时邮箱","uuid":"site-1hnujt4eqaus9t03xx29wo88yot","id":"siteId-1hnujt4eqxyrqe768kkauvuw0gt","type":"web","updatetime":1709350752730},{"bgType":"color","bgColor":"rgba(255,71,52,1)","bgFont":30,"bgText":"谷歌","target":"https://www.linshigmail.com/","name":"谷歌临时邮箱 - 临时Gmail - Google 臨時郵箱","bgColorImage":null,"uuid":"site-1hv1heca53t2p0ozmznr777noy7","id":"siteId-1hv1heca5bfap3o20ora96no4ct","type":"web","updatetime":1716965028165},{"bgType":"image","bgImage":"https://infinitypro-img.infinitynewtab.com/custom-icon/icon-1j67qf67c5lrhrrnbuaf2yx9qdw.png","target":"https://kdown.moiu.cn/","name":"KDown下载","uuid":"site-1j67qf6k41tjh45alaryf0fj780","id":"siteId-1j67qf6k435ipz9oehf1ijlc7nc","type":"web","updatetime":1759051766294,"bgColor":""}]},{"name":"Chrome扩展商店","uuid":"744e698c837a43c49fbd3e26753d7d3f","updatetime":1623332117165,"id":"b0faec62-7048-4cb9-adf6-2b0ad4ccc1cf","target":"https://chrome.google.com/webstore/category/extensions","type":"web","bgImage":"https://infinityicon.infinitynewtab.com/user-share-icon/d2085270ca1ded965bfaac2d2a6b12dc.png","bgType":"image","bgFont":30,"bgText":""},{"name":"游戏","uuid":"8001e439tlmcyc91dk9h3zz04d5eoz","updatetime":1584954005196,"id":"0dbeb45f-dfba-4871-8d65-956415a806a6","children":[{"name":"欢迎来到 Steam","uuid":"8001ecjeqprlgrzym73n4d16up4wiq","updatetime":1594085959539,"id":"fda26931-02e2-46ca-8c85-c6888d633aac","target":"https://store.steampowered.com/","type":"web","bgImage":"https://infinityicon.infinitynewtab.com/user-share-icon/5b3e894fe57dcec58d5680053be2d6c1.png","bgType":"image","bgFont":30,"bgText":""},{"name":"Epic Games | Home","uuid":"d89e5c58c8af4d5dc5094a143d7aa3ea","updatetime":1624021290677,"id":"d5f5102c-131d-4092-8900-0d327adab064","target":"http://epicgames.com","type":"web","bgImage":"https://infinitypro-img.infinitynewtab.com/custom-icon/9001c606srejamirndocjkmp8v13fo.png","bgType":"image","bgFont":30,"bgText":""},{"name":"育碧商城","uuid":"10cd2b349c11ae1cc65510c842749584","bgType":"image","bgImage":"https://infinitypro-img.infinitynewtab.com/custom-icon/9001c8db0pf81crz56p5a21408ifg9.png","updatetime":1635999231906,"id":"siteId-1fjkiebt3vpohv6ksztpzie9029","target":"https://store.ubi.com/cn/home","type":"web"},{"name":"China Play","uuid":"a4a3edb6f5e56741f4a853bb159d60c0","updatetime":1594047473324,"id":"b08bb49e-2c7d-4a4e-87e7-9b0aeec13341","target":"http://chinaplay.store/","type":"web","bgImage":"https://infinitypro-img.infinitynewtab.com/custom-icon/8001crhd5c8v3f7amsxdqpypv2zzzt.png","bgType":"image","bgFont":30,"bgText":""},{"name":"Humble Bundle","uuid":"39edbe548dcea2c231842095b903b801","updatetime":1594047615558,"id":"26144f77-de41-4fac-9189-2d3abbdc2e18","target":"https://www.humblebundle.com/","type":"web","bgImage":"https://infinitypro-img.infinitynewtab.com/custom-icon/9001c29n1t0mmijuzg6bmn2tvj77h7.png","bgType":"image","bgFont":30,"bgText":""},{"name":"Fanatical","uuid":"674e6977dfce95f14f11d7ba1f4db444","updatetime":1594047649296,"id":"bbe6507c-a5d2-48b7-8990-faeda03dfcf6","target":"https://www.fanatical.com/en/","type":"web","bgImage":"https://infinityicon.infinitynewtab.com/user-share-icon/674e6977dfce95f14f11d7ba1f4db444.png","bgType":"image","bgFont":30,"bgText":""},{"name":"Steam数据库·SteamDB","uuid":"8001e6b93p2kqmo6ft5kaqvsf14r95","updatetime":1587369075796,"id":"aab28e25-5e5a-4666-ae1d-a13ebf7b46a7","target":"https://steamdb.info/?__cf_chl_jschl_tk__=7c2752ae3f6b125d460fecd93da891b23cb01afa-1587369040-0-AZSyEqR2ognaJ7pNMvqOv6SCibhWa0o-w_DJHlA-WYd4OGrFK7vl8tZAG2xvdid-nXm0r3-54IKJhomo2KDEZesqOPbYJc4oWkmDjddwtvx67I3SV3bEU8Tvk0I1SaX_GS_OclsN6HI0wkYkJWtHmQvb-KYfX1GHrnwUwk_ImtxpU9f9knGqY6QCoxD1fEj-1koKo7onzF4DAP95zOIUGowe_WZNMooCU7VNo-DPdR6OqERgKkDwTPETJ1GOMwDgUgltEoqvJTccYKv3l0Cuxcw","type":"web","bgType":"color","bgFont":20,"bgText":"SteamDB","bgColor":"#6c4cb9"},{"name":"最新折扣 | 主页 | 10000KEYS | Power By VMShop","uuid":"8001e7mcv55ank72tpnbfoyudi24kj","updatetime":1588815959210,"id":"6e30e234-b65d-48b0-85d5-5630f6c522d2","target":"http://www.10000keys.com/?tdsourcetag=s_pctim_aiomsg","type":"web","bgType":"color","bgFont":14,"bgText":"10000KEYS","bgColor":"#efa738"},{"name":"在 Steam 上激活产品","uuid":"8001e7mcrgmbqcabhi4unxy2bqfly5","updatetime":1588815839947,"id":"d6817d92-e39b-4847-8f78-a693e55c49cc","target":"https://store.steampowered.com/account/registerkey","type":"web","bgType":"color","bgFont":14,"bgText":"Steam激活","bgColor":"#6c4cb9"},{"bgType":"color","bgColor":"rgba(255,110,0,1)","bgFont":14,"bgText":"Battlefield 5","bgImage":"","target":"https://battlefieldtracker.com/","name":"Battlefield 5 Stats, Leaderboards & More! - Battlefield Tracker","bgColorImage":null,"iconType":"color","uuid":"site-1ffjsokljw8m45qhkptecz1k76v","id":"siteId-1ffjsoklkms2psna5s4njvjte77","type":"web","updatetime":1631681532596},{"bgType":"color","bgColor":"rgba(255,71,52,1)","bgFont":20,"bgText":"Cкачать","bgImage":"","target":"https://byrut.org/","name":"Cкачать игры на ПК [последние версии 2021] через торрент бесплатно","bgColorImage":null,"iconType":"color","uuid":"site-1fu0mf12ge2yyvu3g9utkvh07ti","id":"siteId-1fu0mf12gk7qr9v2lp84iwcxv6i","type":"web","updatetime":1647143519312},{"bgType":"color","bgColor":"rgba(255,71,52,1)","bgFont":27,"bgText":"Sw","bgImage":"","target":"https://xxxxx528.com","name":"Switch520","bgColorImage":null,"iconType":"color","uuid":"site-1fu0mggd6ion9jknn940x9py6zh","id":"siteId-1fu0mggd6l8h7ymjmgh5ycmogqf","type":"web","updatetime":1686848631761},{"bgType":"image","bgImage":"https://infinitypro-img.infinitynewtab.com/custom-icon/icon-1h3005qi53w93t1yz5a62igi57d.png","target":"https://laoquzhang.com/","name":"Switch520","uuid":"site-1h3000qdurblyvjfqm1dl7m4yrh","id":"siteId-1h3000qdua268ezy4oof8gdlxvv","type":"web","updatetime":1686848597034},{"bgType":"color","bgColor":"rgba(0,116,255,1)","bgFont":30,"bgText":"Plati","bgImage":"","target":"https://plati.ru/","name":"Plati.Market. Digital goods marketplace.","bgColorImage":null,"iconType":"color","uuid":"site-1fvmtlb87ivj5bysp3oyoc03uxa","id":"siteId-1fvmtlb87kucvzo88gszvs25lxh","type":"web","updatetime":1648963005703},{"bgType":"image","bgImage":"https://infinitypro-img.infinitynewtab.com/custom-icon/icon-1hgdu5tk0y2h8euebyzctz6slen.png","target":"https://battlefieldtracker.com/","name":"Battlefield 2042 Stats, Leaderboards & More! - Battlefield 2042 Tracker","uuid":"site-1hgdu5udp2eiso43qrz3yvmmtwi","id":"siteId-1hgdu5udpkdmpkx45055lgt8yso","type":"web","updatetime":1701274909113},{"bgType":"image","bgImage":"https://infinitypro-img.infinitynewtab.com/custom-icon/icon-1hqro01hn0yq1c00a5d0gdk2ejv.png","target":"https://battlelog.battlefield.com/bf4/","name":"Battlelog / Battlefield 4","uuid":"site-1hqro0216u4esphu7gn63y7m0vj","id":"siteId-1hqro02160dlva4018mvn4l742f","type":"web","updatetime":1712475605030},{"bgType":"image","bgImage":"https://infinitypro-img.infinitynewtab.com/custom-icon/icon-1hjp0ra5lb7m8wk2e97oknxb75q.png","target":"https://wavse.com/","name":"Wavse","uuid":"site-1hjp0rakgzp7z6uj5tzgro36foc","id":"siteId-1hjp0rakg5k6bqq59w30vl0ngfg","type":"web","updatetime":1704868031120},{"bgType":"image","bgImage":"https://infinitypro-img.infinitynewtab.com/custom-icon/icon-1ijf98etk1yfrf8ef8ib67kc1zf.png","target":"https://www.nexusmods.com/","name":"Nexus mods and community","uuid":"site-1ijf98gfbtva3vbw2j9dbaahhqo","id":"siteId-1ijf98gfbq8tm9v0gxxz89crphs","type":"web","updatetime":1738901045739},{"bgType":"image","bgImage":"https://infinitypro-img.infinitynewtab.com/custom-icon/icon-1iprn16eip0xclg4f0epcav3rlr.png","target":"https://juij.fun/#%E7%AB%99%E5%8F%B0%E5%AF%BC%E8%88%AA","name":"dlc解锁 — By. Juij","uuid":"site-1iprn16scxip7jqbzfzth1ke10i","id":"siteId-1iprn16scei5n4kz3h82ys44lnf","type":"web","updatetime":1745760590732}]},{"name":"shopping","uuid":"folder-1fbcdfj7sfzbmnti6xg12a0bi1s","id":"folderId-1fbcdfj7tn5w5a0hcep6ta0zyms","children":[{"name":"天猫精选","uuid":"be0ab26cf4dc6239c98791f7b18b633a","bgType":"image","bgImage":"https://infinityicon.infinitynewtab.com/icon/be0ab26cf4dc6239c98791f7b18b633a.png","updatetime":1627135644133,"id":"siteId-1fbcdf4f5wfhkfeq0mk32x3tyi8","target":"https://s.click.taobao.com/t?infinityType=tmall&e=m%3D2%26s%3DV5ucSP%2F1kT4cQipKwQzePCperVdZeJviK7Vc7tFgwiFRAdhuF14FMRBynALhehQ4RitN3%2FurF3xNWm%2FATOfjswMAKinyMfntv%2FFgqkVH8133BMlVy3qlGE2srC8Mk09eQgZss1jm63jcHtRpEUy6RPalRWTdFmFpJPwiig1bxLMnyi1UQ%2F17I10hO9fBPG8oXH%2BQH9e66Y4%3D","type":"web"},{"name":"京东商城","uuid":"6dcbbe4e9dc6ef2fd68da7d8befd117c","bgType":"image","bgImage":"https://infinityicon.infinitynewtab.com/user-share-icon/cee009549b352def723ba09d6da4b742.png","updatetime":1627135641617,"id":"siteId-1fbcdf20hlghhuet62yk4z8e0r0","target":"https://www.infinitynewtab.com/jd.pro.html ","type":"web"},{"bgType":"image","bgImage":"https://infinitypro-img.infinitynewtab.com/custom-icon/icon-1ggth1h0sh09q7msbg19iriugg2.png","target":"https://www.taobao.com/","name":"淘宝网 - 淘！我喜欢","uuid":"site-1ggth1ha52umsbs7fjkbyijr2lw","id":"siteId-1ggth1ha5ykvt6ec660zis9w1fr","type":"web","updatetime":1667438265669},{"name":"zFrontier 装备前线","uuid":"74ffb375348c5b893ff1ffdeabaab877","bgType":"image","bgImage":"https://infinitypro-img.infinitynewtab.com/custom-icon/9001c762p3og8oz8yimsp83qw93mk7.png","updatetime":1673248717560,"id":"siteId-1gmamaenpuaod4bypa8f665pvb8","target":"https://www.zfrontier.com/","type":"web"}],"updatetime":1627135679825},{"name":"硬件学习","uuid":"folder-1ffojd3nj24tmh3t6m1km6q6xn0","id":"folderId-1ffojd3njyrty9hkvwmp8e3xul6","children":[{"name":"BOSS直聘","uuid":"126cb246c0dd7a3c7f7169ae1ac21d36","bgType":"image","bgImage":"https://infinitypro-img.infinitynewtab.com/custom-icon/9001c90n578jxi0afnmr6dzg3rche8.png","updatetime":1757232489086,"id":"siteId-1j4hjfojum18u66tx4n5ciddeqc","target":"https://www.zhipin.com/","type":"web"},{"bgType":"image","bgImage":"https://infinitypro-img.infinitynewtab.com/custom-icon/icon-1j5l9ilqdim2krop14po3i4qoor.png","target":"https://www.jlc.com/","name":"嘉立创科技集团股份有限公司","uuid":"site-1j5l9im2661uw2u6ouo47dclbu8","id":"siteId-1j5l9im26ykcyllekbdx2gshoaf","type":"web","updatetime":1758430058566},{"bgType":"image","bgImage":"https://infinitypro-img.infinitynewtab.com/custom-icon/icon-1j4r2u9hpz6v33vn8a9oaxp9zw4.png","target":"https://www.szlcsc.com/","name":"立创商城_一站式电子元器件采购自营商城_嘉立创电子商城","uuid":"site-1j4r2u9qu4ckgc94acqhtyv4nsn","id":"siteId-1j4r2u9quzu53ifjkmnwa1e8fag","type":"web","updatetime":1757550695386,"bgColor":""},{"bgType":"image","bgImage":"https://infinitypro-img.infinitynewtab.com/custom-icon/icon-1j5mc2ftd6jf9rhx5a6lb2f1exn.png","target":"https://www.hqchip.com/","name":"华秋商城(原\"华强芯城\")官网_电子元器件采购网_自营现货电子元器件商城-一站式电子元器件商城","uuid":"site-1j5mc2g44z2htih1iy8vw0qa30f","id":"siteId-1j5mc2g44f5w6fgv18jeonqbwn5","type":"web","updatetime":1758466228356},{"bgType":"image","bgImage":"https://infinitypro-img.infinitynewtab.com/custom-icon/icon-1j4r2vnmox4f6n2emoh6w582pg7.png","target":"https://semiee.com/","name":"半导小芯-芯片查询工具_芯片替代查询_数据手册查询_规格书查询_datasheet查询_IC查询_国产替代","uuid":"site-1j4r2vo0n7i9o0451ctqscogcvr","id":"siteId-1j4r2vo0nwfebx668hmvf964b0w","type":"web","updatetime":1757550731287},{"bgType":"image","bgImage":"https://infinitypro-img.infinitynewtab.com/custom-icon/icon-1htt5rh3317jjw8x2of38g16x1y.png","target":"https://www.programmercarl.com/","name":"代码随想录","uuid":"site-1htt5rhgviy3v175xpfhyy8f1n5","id":"siteId-1htt5rhgvpssyispik1u2iw3kdz","type":"web","updatetime":1715744917023},{"bgType":"color","bgColor":"rgba(60,15,15,1)","bgFont":30,"bgText":"An","target":"https://annas-archive.li/","name":"Anna's Archive电子书","bgColorImage":null,"uuid":"site-1ide7fon31d54qu1w7ndbfl1pug","id":"siteId-1ide7fon3e71ddi5ofy95j05h5q","type":"web","updatetime":1732423245025},{"bgType":"image","bgImage":"https://infinitypro-img.infinitynewtab.com/custom-icon/icon-1j4a5tbmvqilge0oza97ktinjs4.png","target":"https://www.badcaps.net/","name":"Badcaps - Laptop, TV, & Other Electronics Repair Forum - Badcaps","uuid":"site-1j4a5tbtc47la4hdisojtx5otfr","id":"siteId-1j4a5tbtcqcn6cqnztc325u1f6r","type":"web","updatetime":1756983373740},{"bgType":"color","bgColor":"rgba(255,71,52,1)","bgFont":30,"bgText":"华强","target":"https://www.hqew.com/","name":"华强电子网-IC/电子元器件材料采购交易平台 Hqew.com","bgColorImage":null,"uuid":"site-1j5mcaotkddpw76u90yywh8k4lu","id":"siteId-1j5mcaotko5uyhs1zjqczdwf3sn","type":"web","updatetime":1758466499508},{"bgType":"image","bgImage":"https://infinitypro-img.infinitynewtab.com/custom-icon/icon-1j5mcdsogy26toy0kpvpn5hr1k7.png","target":"https://www.oneyac.com/","name":"唯样商城_电子元器件采购网上商城_电子元器件目录授权分销商","uuid":"site-1j5mcdt3ozznzpsk571rk2oyynh","id":"siteId-1j5mcdt3oeanpmm89j5zcgtzma2","type":"web","updatetime":1758466602104},{"bgType":"image","bgImage":"https://infinitypro-img.infinitynewtab.com/custom-icon/icon-1j75u4mgrd511dyns568n6pgfkr.png","target":"https://iotdebug.com/","name":"串口调试助手","uuid":"site-1j75u4mq3u7xtu4lke3a1jkr5up","id":"siteId-1j75u4mq3kdeg3e70bfkrzjy4gv","type":"web","updatetime":1760062233411}],"updatetime":1757550577665},{"name":"AI","uuid":"folder-1h0rnv5naw9sjzo4ppff0e9bfw6","id":"folderId-1h0rnv5na4fn72ve181f1wcbbzu","children":[{"uuid":"site-1h0rnt9od0g0s7ybzdg3edio4pt","id":"siteId-1h0rnt9od56s4k3snrzxqg3v803","type":"web","bgType":"image","bgImage":"https://infinitypro-img.infinitynewtab.com/custom-icon/icon-1h0rnt7rcizhxgm2k9mksvyhymm.png","target":"https://chatgpt.com/","name":"ChatGPT","updatetime":1730611721260,"bgColor":""},{"uuid":"site-1h0rnv2e87u1a1dk4qfqgvd3pot","id":"siteId-1h0rnv2e8fv6nefmbi6kon05rmz","type":"web","bgType":"color","bgColor":"rgba(74,197,125,1)","bgFont":30,"bgText":"Ch8","target":"https://chat86.co/638146","name":"Chat8","bgColorImage":null,"updatetime":1684558285255},{"bgType":"image","bgImage":"https://infinitypro-img.infinitynewtab.com/custom-icon/icon-1hnacdapts0lypaxk8axht4jl51.png","target":"https://www.coze.com/home","name":"Home - Coze","uuid":"site-1hnacdb4f90ogfxk6opolpyg16p","id":"siteId-1hnacdb4f786mn4kengah82lmu6","type":"web","updatetime":1708671806607},{"bgType":"image","bgImage":"https://infinitypro-img.infinitynewtab.com/custom-icon/icon-1hrqkqgdvahlguxc4jxriw338gm.png","target":"https://chatglm.cn/main/alltoolsdetail","name":"智谱清言AI","uuid":"site-1hrqkqgqkx7mi493o9kyhz6fhzr","id":"siteId-1hrqkqgqkfaeqasvj90iiyklna0","type":"web","updatetime":1713512465236},{"bgType":"image","bgImage":"https://infinitypro-img.infinitynewtab.com/custom-icon/icon-1hut6acjeqxps2v7r15c2uoacx1.png","target":"https://mychandler.bet/chat","name":"ChandlerAi","uuid":"site-1hut6acucm6b0b07we6cfhz7orz","id":"siteId-1hut6acuc7f1mfxbai78smlpz89","type":"web","updatetime":1716819145676},{"bgType":"color","bgColor":"rgba(255,207,12,1)","bgFont":30,"bgText":"GPT","target":"https://gpt.github.cn.com/","name":"GPTcn","bgColorImage":null,"uuid":"site-1i0n4p47bld8jjuh646wyf2nfut","id":"siteId-1i0n4p47bdjq8r8pjaljg8xfnnp","type":"web","updatetime":1718763688171},{"bgType":"image","bgImage":"https://infinitypro-img.infinitynewtab.com/custom-icon/icon-1i2gjmc5e9vn4vygljx1uv3khea.png","target":"https://www.opkfc.com/list","name":"数字玩家","uuid":"site-1i2gjmch7d2hae1sauf1cpvh7ng","id":"siteId-1i2gjmch7ynfjtp5w3qzi7ovexj","type":"web","updatetime":1720691929639},{"bgType":"image","bgImage":"https://infinitypro-img.infinitynewtab.com/custom-icon/icon-1ikpptkll23oqc46y65nsedf6it.png","target":"https://yuanbao.tencent.com/chat/naQivTmsDa","name":"腾讯元宝","uuid":"site-1ikpptl1c0klttxsjhyvs4ybf5i","id":"siteId-1ikpptl1c7enoawwkjnm6v6eze5","type":"web","updatetime":1740327835557,"bgColor":""},{"bgType":"image","bgImage":"https://infinitypro-img.infinitynewtab.com/custom-icon/icon-1i5ah2ig22b6nq6362geot41elp.png","target":"https://new.oaifree.com/","name":"ChatGPT镜像","uuid":"site-1i5ah2istuo9n4bz4i5bdda4g8u","id":"siteId-1i5ah2istn9vnp4esqe890oojp5","type":"web","updatetime":1723709082525},{"bgType":"image","bgImage":"https://infinitypro-img.infinitynewtab.com/custom-icon/icon-1i9td46moroydji5ls3tn1vi6ed.png","target":"https://www.qianwen.com/","name":"千问-Qwen最新模型体验-通义千问","uuid":"site-1i9td472dppxxuslkclkixurhjc","id":"siteId-1i9td472d59rq2n215l4jx058jc","type":"web","updatetime":1763957852715,"bgColor":""},{"bgType":"image","bgImage":"https://infinitypro-img.infinitynewtab.com/custom-icon/icon-1igo7dpm11jxdyao8h4gay12mtn.png","target":"https://chat.deepseek.com/","name":"DeepSeek - 探索未至之境","uuid":"site-1igo7dq0mkwgmaslu8g0ifgyc8o","id":"siteId-1igo7dq0mlh9d5m5f54c35vof5x","type":"web","updatetime":1735979886614},{"bgType":"image","bgImage":"https://infinitypro-img.infinitynewtab.com/custom-icon/icon-1igr1s70tig3hqoc495vba2c0xy.png","target":"https://kimi.moonshot.cn/","name":"Kimi.ai - 会推理解析，能深度思考的AI助手","uuid":"site-1igr1s7a41kc5hsnoma0co1m440","id":"siteId-1igr1s7a4tpn5smxx85iauh2z5k","type":"web","updatetime":1736074730820},{"bgType":"image","bgImage":"https://infinitypro-img.infinitynewtab.com/custom-icon/icon-1j8ktfeng6npq1axt255yf6p35k.png","target":"https://civitai.com/","name":"Civitai: The Home of Open-Source Generative AI","uuid":"site-1j8ktfeu1tu8u4uivdgtf1z2h9z","id":"siteId-1j8ktfeu1e8fu3q7j90tjv1hq72","type":"web","updatetime":1761638595521},{"bgType":"image","bgImage":"https://infinitypro-img.infinitynewtab.com/custom-icon/icon-1jado2ngszshcsejp43857ab50j.png","target":"https://huggingface.co/","name":"Hugging Face – The AI community building the future.","uuid":"site-1jado2o900ml4i30v1ev4m0zlvh","id":"siteId-1jado2o90duykx9imis43jaefnp","type":"web","updatetime":1763545538848},{"bgType":"image","bgImage":"https://infinitypro-img.infinitynewtab.com/custom-icon/icon-1j9jorscjfjwukus4j41fhzz2f8.png","target":"https://www.doubao.com/chat/","name":"豆包 - 字节跳动旗下 AI 智能助手","uuid":"site-1j9jort1f4s85ch64p7j0j8lfjz","id":"siteId-1j9jort1f9xn763kqqilezoiqr5","type":"web","updatetime":1762673947695},{"uuid":"site-1jas9fmtlhptr2gxjs7i9whatp2","id":"siteId-1jas9fmtlv9ob5es4m5n31ae55d","type":"web","bgType":"image","bgImage":"https://infinitypro-img.infinitynewtab.com/custom-icon/icon-1jas9fmgqinjs5mt4f53wu1w983.png","target":"https://dify.ai/","name":"Dify: Leading Agentic Workflow Builder","updatetime":1764033551284},{"bgType":"image","bgImage":"https://infinitypro-img.infinitynewtab.com/custom-icon/icon-1jb9k2igae5x7gpw3co5xo0ik6a.png","target":"https://gemini.google.com/app","name":"Google Gemini","uuid":"site-1jb9k2j248ne6q10af4eaptm21z","id":"siteId-1jb9k2j242e22kn1u8kl1se7t7q","type":"web","updatetime":1764480863300},{"bgType":"color","bgColor":"rgba(255,71,52,1)","bgFont":30,"bgText":"提示","target":"https://opennana.com/awesome-prompt-gallery/","name":"提示词案例库","bgColorImage":null,"uuid":"site-1jb57aelf26i418rgndmqg7op83","id":"siteId-1jb57aelfx1602ui1gy4ptwrr9c","type":"web","updatetime":1764480898205}],"updatetime":1761638613211}],[{"name":"小程序","uuid":"folder-1igji7bhqvzr5jmtqtddwva9km4","id":"folderId-1igji7bhqbqhuhzfjuud33phe4i","children":[{"bgType":"image","bgImage":"https://infinitypro-img.infinitynewtab.com/custom-icon/icon-1iginrkjgdsecqydcg7u4txiib7.png","target":"https://developers.weixin.qq.com/miniprogram/dev/framework/","name":"微信开放文档 / 开发","uuid":"site-1iginrlf7brra7jcekkptjn2a7n","id":"siteId-1iginrlf7bu6p3v411ig4wdjc7h","type":"web","updatetime":1735795791335},{"bgType":"image","bgImage":"https://infinitypro-img.infinitynewtab.com/custom-icon/icon-1in8edfp2wqpunp66eukn2szmg0.png","target":"https://mp.weixin.qq.com/wxamp/home/guide?lang=zh_CN&token=198141765","name":"微信小程序","uuid":"site-1in8edg5c7vjp51fhkqxep98hky","id":"siteId-1in8edg5crfhogn96yi6xxfxtde","type":"web","updatetime":1742966538412},{"bgType":"image","bgImage":"https://infinitypro-img.infinitynewtab.com/custom-icon/icon-1igj167uql97rbigp7yu9ruwtaj.png","target":"https://tcb.cloud.tencent.com/dev?/overview","name":"云开发平台","uuid":"site-1igj1688py05f8ylm1y82egy7nj","id":"siteId-1igj1688p6euf9d2fveaokgw08g","type":"web","updatetime":1735805587940,"bgColor":""},{"bgType":"image","bgImage":"https://infinitypro-img.infinitynewtab.com/custom-icon/icon-1igji8jstarfiqirvpq5h971sr1.png","target":"https://www.iconfont.cn/home/index","name":"iconfont-阿里巴巴矢量图标库","uuid":"site-1igji8k86kefjqmnzyyayncvpme","id":"siteId-1igji8k869nmr3mhn0h3xnqvezr","type":"web","updatetime":1735823479046},{"bgType":"image","bgImage":"https://infinitypro-img.infinitynewtab.com/custom-icon/icon-1i9oogbmcgcw4qjjtmrf3knrn3a.png","target":"https://vant-ui.github.io/vant-weapp/#/home","name":"介绍 - Vant Weapp","uuid":"site-1i9oogc3roixbz8orosz6fbwaan","id":"siteId-1i9oogc3rnb6n9tkarxs7w7yscp","type":"web","updatetime":1728481603707}],"updatetime":1735823443172},{"name":"公司","uuid":"8001djeqod3d8b7sv7xbwj3j5w9zaq","updatetime":1567087146094,"id":"f9a6eb2d-ba62-4a73-ba57-fbc64e5e2efd","children":[{"name":"越秀物业（珠三角）（new）","uuid":"8001e6qe3d07crri342ijcx9ty4wyp","updatetime":1587877622791,"id":"d9e2b736-6d15-4814-8373-6a2ccb81066f","target":"https://oa.yuexiuproperty.cn/web/#/1e488nmtmw1gw5o03w219rgn534ifbel28w0/sys-portal/1e488nmtrw1gw5o09wp4l4ac1ac3ueb245w0","type":"web","bgType":"color","bgFont":34,"bgText":"越秀","bgColor":"#efa738"},{"name":"订单管理","uuid":"8001djeqbkr41qybb1ve3ekbehd8ol","updatetime":1567086728036,"id":"8bb3f8ea-32c9-4b54-b4bb-bb36b713f0da","target":"http://enjoy-club-m.yuexiuproperty.cn/Order/ShopOrder","type":"web","bgType":"color","bgFont":34,"bgText":"订单","bgColor":"#efa738"},{"name":"车场云管理平台","uuid":"8001djeqg0ljvfstlx3tp3brhzfi93","updatetime":1567087142517,"id":"12c2a28f-efc5-4524-be3d-27e8f6b1c551","target":"https://pmc.airparking.cn/pmcp/index","type":"web","bgType":"color","bgFont":34,"bgText":"车场","bgColor":"#efa738"},{"name":"开票服务器管理系统【914420005814069808.1】","uuid":"8001djeqel6rihze1yz4j4vkddp632","updatetime":1567087136478,"id":"a4c8d8f6-0022-4223-ae2f-ba498fe2233e","target":"http://183.63.137.101:11001/914420005814069808_1/login.jsp","type":"web","bgType":"color","bgFont":34,"bgText":"开票","bgColor":"#efa738"}]},{"name":"工具箱","uuid":"8001e4536mtl1fyil49fd0u9ykydia","updatetime":1735859866590,"id":"0053f3f1-bac5-4674-9d5f-88688a55dcb4","children":[{"name":"APKCombo: #1 APK Downloader - 下载 APK & OBB (免费)","uuid":"8001dqc4havqjhjd3pv7u09agajvbq","updatetime":1574512929786,"id":"2c506e7f-f7bf-47ba-8e9e-9fd7b836b670","target":"https://apkcombo.com/zh-cn/","type":"web","bgType":"color","bgFont":34,"bgText":"APK","bgColor":"#df5f47"},{"name":"Office 模板和主题","uuid":"8001dqbciq2qh3meqcha1vkfbn8noc","updatetime":1574487812186,"id":"ac57d750-caf9-4d91-8bb0-85fe0f077ced","target":"https://templates.office.com/","type":"web","bgType":"color","bgFont":29,"bgText":"Office","bgColor":"#faec63"},{"name":"星空软件共享绿化园地","uuid":"8001dukgtchgpe3it14ur2r57rhv2l","updatetime":1579089310256,"id":"28b81e6f-2a05-46d8-8fdf-dc20a98b8441","target":"http://www.xingkbjm.com/","type":"web","bgType":"color","bgFont":20,"bgText":"星空软件","bgColor":"#73b364"},{"name":"千鹤导航 | 聚合最优质资源网站！","uuid":"8001duktsaklr7xs2iewdbef4b42u1","updatetime":1579102907029,"id":"968d0f30-5a43-4b10-929a-4b648566a567","target":"https://www.qianhedh.com/","type":"web","bgType":"color","bgFont":21,"bgText":"千鹤导航","bgColor":"#6c4cb9"},{"name":"马小帮 | 专注于互联网科技经验分享！","uuid":"8001dshb1ta7ytajcelaqio498kqca","updatetime":1576835020103,"id":"3e3a6b22-3a87-4295-9fbd-c760911c3298","target":"https://www.maxiaobang.com/","type":"web","bgType":"color","bgFont":28,"bgText":"马小帮","bgColor":"#df5f47"},{"name":"秘塔写作猫","uuid":"8001dtfvigram2uc0w13cli2kwlsjg","updatetime":1577863168874,"id":"ecbdce58-5ac6-41ff-9e8c-5871a5fc12d3","target":"https://xiezuocat.com/#/","type":"web","bgType":"color","bgFont":34,"bgText":"写作猫","bgColor":"#57a0ee"},{"name":"果核剥壳 - 还原软件的本质","uuid":"8001ds1kvt4hbaiyp72r7di74yf82n","updatetime":1576308569233,"id":"69594555-efe3-41b3-af39-b215c4e4d37a","target":"https://www.ghpym.com/","type":"web","bgType":"color","bgFont":34,"bgText":"果核","bgColor":"#efa738"},{"name":"首页 - 孟坤工具箱网页版","uuid":"8001dsiuof7ha4j27ooqj4sextwfa4","updatetime":1576889236721,"id":"e0a0a09e-b091-40e0-bcc8-752a246d337a","target":"http://tool.mkblog.cn/","type":"web","bgType":"color","bgFont":28,"bgText":"工具箱","bgColor":"#df5f47"},{"name":"Creations - Panzoid","uuid":"8001dppqehmgq5840jmeov4ldkic54","updatetime":1573898372816,"id":"c33ff6ab-7cba-47bd-9349-837c56ab6394","target":"https://panzoid.com/creations","type":"web","bgType":"color","bgFont":34,"bgText":"Cr","bgColor":"#6c4cb9"}]},{"name":"云短信 - 在线短信接收","uuid":"8001e48gao9jh15jr6th9mmhvn635m","updatetime":1585128497459,"id":"3b7aa888-f370-4830-af19-9d0dde9a2e06","target":"https://www.materialtools.com/","type":"web","bgType":"color","bgFont":23,"bgText":"云短信","bgColor":"#57a0ee"}],[{"name":"风灵月影修改器整理发布帖 (长期更新中) - 游戏杂谈区 - 3DMGAME论坛 - Powered by Discuz!","uuid":"8001e4abeiiug5t6hvmspuadcqavth","updatetime":1585190488670,"id":"affea01a-6b78-46d1-a572-84f8f7e2b442","target":"https://bbs.3dmgame.com/thread-6018798-1-1.html","type":"web","bgType":"color","bgFont":22,"bgText":"修改器","bgColor":"#efa738"},{"name":"ArtStation - _Z eD_","uuid":"8001e4l9gm0rx1jeof27a8840stidv","updatetime":1585557559323,"id":"e9c1a22e-526e-42c0-b608-03ab7dcb9fce","target":"https://www.artstation.com/trungbui42","type":"web","bgType":"color","bgFont":16,"bgText":"ArtStation","bgColor":"#df5f47"},{"name":"MyDock MyFinder 官网","uuid":"8001e4nkthdvifrr79lb3n1wl6sbsn","updatetime":1585636623807,"id":"f7ce4a58-b146-4309-8139-655908fd0966","target":"https://www.mydockfinder.com/index.html#time=14&NewVariable1=1&CSUM=1","type":"web","bgType":"color","bgFont":20,"bgText":"MyDock","bgColor":"#57a0ee"},{"name":"E-Hentai Forums","uuid":"8001e4t14g9ne54at77voh3u6q4hbo","updatetime":1585817207095,"id":"5abdef3a-3e62-4311-a206-da21cc6a3906","target":"https://forums.e-hentai.org/index.php?","type":"web","bgType":"color","bgFont":19,"bgText":"E-Hentai","bgColor":"#60c0d6"},{"name":"Artist Galleries ::: Sakimichan - E-Hentai Galleries","uuid":"8001e4t4hjd61rxe6vk2k9zjgpm1js","updatetime":1585820781990,"id":"237d3f95-b62a-456e-ab7f-5379b7a4f7d3","target":"https://e-hentai.org/g/1600055/013171acd3/","type":"web","bgType":"color","bgFont":14,"bgText":"Sakimichan","bgColor":"#df5f47"}],[{"name":"文件夹","uuid":"folder-1f9c3e6eoztx77x10jf2mm4t3jf","id":"folderId-1f9c3e6eoaqgppyajhftjy2r49f","children":[{"name":"米诺米诺米的个人主页 - 半次元 - ACG爱好者社区","uuid":"8001e6v88tbufiff5aq1pavql2rttx","updatetime":1588039284094,"id":"e4341f85-fbb7-4401-b824-96f87ade01ec","target":"https://bcy.net/u/2535475","type":"web","bgType":"color","bgFont":34,"bgText":"米诺","bgColor":"#efa738"},{"bgType":"color","bgColor":"rgba(255,71,52,1)","bgFont":30,"bgText":"牛C","bgImage":"","target":"https://www.niucme.workers.dev/","name":"牛C网导航 | 强大的老司机福利导航网！","bgColorImage":"https://infinitypro-img.infinitynewtab.com/custom-icon/icon-1f9486uh4cfmybafl02nc8sx1eo.png","iconType":"color","uuid":"site-1f94870qopaca0qw36i1o2lbojf","id":"siteId-1f94870qopzb6cgnrunbomnnmzh","type":"web","updatetime":1624714216280},{"name":"炫猿 | 炫猿","uuid":"8001e71m50a7zpr43i2ntanxfmnrjb","updatetime":1588120944967,"id":"c77ebb9e-f338-4837-83df-803960bc1761","target":"https://xydh.fun/","type":"web","bgType":"color","bgFont":34,"bgText":"炫猿","bgColor":"#6c4cb9"}],"updatetime":1624977643992},{"name":"Logoly.Pro —— A creative Logo Generator","uuid":"8001echoubqs9zozy2q4rf4kld5g4i","updatetime":1594029453148,"id":"1996dc67-acb4-42fa-a806-d11f8b26b2d5","target":"https://www.logoly.pro/#/","type":"web","bgType":"color","bgFont":17,"bgText":"Logoly.Pro","bgColor":"#efa738"},{"name":"GBT小组游戏空间","uuid":"8001ef38g7o18gaw2d9juw56j1rzlv","updatetime":1596763676417,"id":"c4e11bab-dd28-4ddc-81c1-24c652d93dba","target":"http://renxufeng.ys168.com/","type":"web","bgType":"color","bgFont":14,"bgText":"GB游戏空间","bgColor":"#73b364"},{"bgType":"color","bgColor":"rgba(44,214,223,1)","bgFont":20,"bgText":"网盘映射","bgImage":"","target":"http://localhost:9798/","name":"CloudDrive /","bgColorImage":null,"iconType":"color","uuid":"site-1fdi8qfjbb6yvb115axqa4egugp","id":"siteId-1fdi8qfjbxk1i7n67ki7rfm2c61","type":"web","updatetime":1629479583339},{"name":"文件夹","uuid":"folder-1g6i22nhirlbme84jorq58741ha","id":"folderId-1g6i22nhip0hfi35rvns365rtoo","children":[{"bgType":"color","bgColor":"rgba(255,71,52,1)","bgFont":30,"bgText":"动漫","bgImage":"","target":"https://anime-pictures.net/?lang=zh_CN","name":"动漫图片和壁纸","bgColorImage":null,"iconType":"color","uuid":"site-1fj3frlg7fbjebdjd67xdbu0qc6","id":"siteId-1fj3frlg7vyheyhetijiqnbenv3","type":"web","updatetime":1635426096647},{"name":"动漫图片和壁纸","uuid":"8001ejngs31lxnczux2bea9m0b1flc","updatetime":1601738509365,"id":"66f0ec9e-9ee7-4a08-987d-964a412f2b5b","target":"https://anime-pictures.net/","type":"web","bgType":"color","bgFont":34,"bgText":"动漫","bgColor":"#57a0ee"}],"updatetime":1656316059186}],[{"bgType":"color","bgColor":"rgba(255,71,52,1)","bgFont":30,"bgText":"LD","bgImage":"","target":"https://ldtstore.com.cn/ldtools/","name":"LDTools - LaodiTeachTips","bgColorImage":null,"iconType":"color","uuid":"site-1frfi2bhoi461txoe9yux2bxync","id":"siteId-1frfi2bhoijqzl5vgs2x8uycmfj","type":"web","updatetime":1644421000760},{"bgType":"image","bgImage":"https://infinitypro-img.infinitynewtab.com/custom-icon/icon-1geujpees2nhsphsdvmo1u3rx9x.png","target":"https://ai.nya.la/image","name":"Image Generation - NovelAI","uuid":"site-1geujpeo8pgp5phgkazjq72s870","id":"siteId-1geujpeo8s2pyzwetqya7vb0bsy","type":"web","updatetime":1665327217416},{"bgType":"image","bgImage":"https://infinitypro-img.infinitynewtab.com/custom-icon/icon-1h60s3840sjcgaidqclnocajdeg.png","target":"https://haoka.lot-ml.com/login.html","name":"172号卡分销系统","uuid":"site-1h60p484lzamigzlqqwbohpvdjp","id":"siteId-1h60p484lxdu6pqicwnoxtn1xz4","type":"web","updatetime":1690099099915},{"bgType":"image","bgImage":"https://infinitypro-img.infinitynewtab.com/custom-icon/icon-1hall01hfm711bq3jvyv4av976e.png","target":"https://www.nvidia.cn/Download/Find.aspx?lang=cn%C2%A0","name":"Official Advanced Driver Search | NVIDIA","uuid":"site-1hall0i64wwjeu3mpeh1aivus4i","id":"siteId-1hall0i640yq15z57h5cgnrk2y5","type":"web","updatetime":1695091280068},{"bgType":"image","bgImage":"https://infinitypro-img.infinitynewtab.com/custom-icon/icon-1ieita9u53ldqlwmquiyvlhknhy.png","target":"https://gezhe.com/","name":"歌者 PPT - 永久免费的 PPT 智能生成工具","uuid":"site-1ieitaaaf0mm8qv0rymbid1g2t0","id":"siteId-1ieitaaaf8ta6w5pp29hbbou7t7","type":"web","updatetime":1733654030671},{"bgType":"image","bgImage":"https://infinitypro-img.infinitynewtab.com/custom-icon/icon-1if0gm85848y8s1k735hc0v0ueq.png","target":"https://map.caimogu.cc/wxnn/world.html","name":"世界地图 - 无限暖暖 - 踩蘑菇互动地图","uuid":"site-1if0gm8i6mip2mg7xjpepazeg6p","id":"siteId-1if0gm8i6eibz70fn2lfj5gcyxg","type":"web","updatetime":1734110552646},{"bgType":"image","bgImage":"https://infinitypro-img.infinitynewtab.com/custom-icon/icon-1ij3c180pfgjrfzav66i37zl835.png","target":"https://jx.11qr.com/user/parse","name":"网盘解析-GY","uuid":"site-1ij3c18bezi9zzdhs6nq7fdz95v","id":"siteId-1ij3c18beboxa9vvgp14g9hkmme","type":"web","updatetime":1738501300590}],[{"bgType":"image","bgImage":"https://infinitypro-img.infinitynewtab.com/custom-icon/icon-1it6v1tqb09zydp1a6liou6z7f7.png","target":"https://via.ygtq.fun/","name":"VIA","uuid":"site-1it6v1u3vjyx4fokrfw8bk705pr","id":"siteId-1it6v1u3vy765tq9b2b0enevnze","type":"web","updatetime":1749359327359},{"bgType":"image","bgImage":"https://infinitypro-img.infinitynewtab.com/custom-icon/icon-1j4gpg63cdtx4ikfkuho19pqcpn.png","target":"https://xd.x6d.com/","name":"小刀娱乐网 - 专注活动，软件，教程分享！总之就是网络那些事。","uuid":"site-1j4gpg6ec9u1qbm4v8djj8wah2b","id":"siteId-1j4gpg6ecopvqfjt0337vvotzwh","type":"web","updatetime":1757205240268}]]},"setting":{"setting":{"notice":{"gmail":false,"gmailVoice":false,"gmailNumber":false,"todoNumber":false},"link":{"icon":false,"search":false,"bookmark":false,"history":false},"view":{"topBookmark":false,"topUseful":false,"windmill":true,"pagin":false,"hideInfinityAI":false,"isShowHomepageBtn":true,"isHideIcp":true,"scaleSide":0.73,"scaleMain":1},"layout":{"row":2,"col":5,"rowGap":0.2,"colGap":0.3,"custom":false,"customItem":[2,5]},"animation":{"easing":"elastic"},"icon":{"miniMode":false,"shadow":true,"startAnimation":false,"opacity":0.86,"radius":0.5,"scale":0.5,"isHideIconName":false},"search":{"hide":false,"searchSuggest":true,"keepSearchInput":false,"hideCategory":false,"hideButton":false,"shadow":true,"scale":0.8,"radius":0.14,"opacity":0.8},"font":{"shadow":true,"size":14,"color":"rgba(255,255,255,0.8)"},"_v1Setting":{"isAutoSync":true,"presetColumn":2,"presetRow":5,"location":"","tempUnitC":true,"lastWallpaperId":""}}},"wallpaper":{"id":"57c8e93710b51d256eec393f","url":"https://infinitypro-img.infinitynewtab.com/findaphoto/bigLink/17056.jpg?imageView2/2/w/2560/format/webp/interlace/1","rawUrl":"https://infinitypro-img.infinitynewtab.com/findaphoto/bigLink/17056.jpg","wpSource":"all","type":"cloudAuto","switchType":"twelve-hour","color":"#df5f47","timeEnd":1764736266978,"index":-1,"opacity":21,"blur":0,"cloudRecentUsed":["57c8ef1110b51d256eec3981","61838cb685b89966c0bf3b49","61838cb885b89966c0bf54f4","57cb358ccc8e0d025ab9cee7","61838cbb85b89966c0bf7800","61838caf85b89966c0beff14","61838cc185b89966c0bfba30","61838cbf85b89966c0bfab04","61838cc485b89966c0bfe116","57cb29c0b57de202953056fb","57cb19c1cc8e0d025ab9ce06","58175fd3df4f792e31cfb3f7","61838cb685b89966c0bf3f58","61838cc485b89966c0bfe352","61838cbe85b89966c0bf9811","61838cb785b89966c0bf4343","61838caf85b89966c0beff93","57cb1b7cb57de20295305663","61838cb385b89966c0bf1da7","61838cbe85b89966c0bf9b61","5816ef98df4f792e31cfb043","61838cbf85b89966c0bfa87d","61838cb785b89966c0bf419e","61838cc385b89966c0bfd252","61838cb785b89966c0bf46d7","61838cbb85b89966c0bf7b53","61838cba85b89966c0bf694e","61838cc785b89966c0c00449","61838cc585b89966c0bff652","57caf0cdb57de202953054ad","678539afd0a997bae4c97f7b","67868b2f21aea7bafd11109e","6787dcaf21aea7bafd11134f","67892e2f99ae35badee76713","678a7fb0d0a997bae4c989ed","678bd12fd0a997bae4c98b9b","678d22afd0a997bae4c98d27","678e742f99ae35badee76f00","678fc5b0d0a997bae4c991ee","6791172f2ab932baf64f979c","679268af21aea7bafd1124f5","6793ba2f21aea7bafd112751","67950baf99ae35badee778e9","67965d2f21aea7bafd1129f5","6797aeaf2ab932baf64f9fce","6799002f21aea7bafd112c57","679a51b021aea7bafd112d8c","679cf4af2ab932baf64fa3a9","679e462f99ae35badee7823b","679f97af21aea7bafd1132c7","67a0e92f21aea7bafd1135cc","67a23aafd0a997bae4c9a928","67a38c2f2ab932baf64faefe","67a4ddafd0a997bae4c9adfc","67a62f2fd0a997bae4c9b12b","67a780af99ae35badee792b1","67a8d22f99ae35badee7942c","67aa23af21aea7bafd11473e","67ab752f2ab932baf64fbe43","67acc6af21aea7bafd114cff","67ae182f99ae35badee79ff8","67af69af21aea7bafd11532a","61838cba85b89966c0bf68dd","67b0bb2fd0a997bae4c9c52c","67b20caf99ae35badee7a67c","67b4afaf99ae35badee7ad01","67b6012f99ae35badee7b0fd","67b8a42f99ae35badee7bb15","67b9f5af21aea7bafd116ecd","67bb472f2ab932baf64fe333","67bc98af99ae35badee7c2cf","67bdea2f99ae35badee7c62a","67bf3baf2ab932baf64fefda","67c08d2fd0a997bae4c9f221","67c1deaf99ae35badee7d486","67c3302f99ae35badee7d67c","67c481af99ae35badee7d825","67c5d58821aea7bafd119018","67c724af99ae35badee7e75e","67c8762f21aea7bafd119c11","67c9c7af99ae35badee7ee30","67cb192f99ae35badee7f139","67cc6aafd0a997bae4ca13c1","67cdbc2fd0a997bae4ca15ad","67cf0dafd0a997bae4ca18c5","67d05f2f99ae35badee7fb1e","67d1b0afd0a997bae4ca214d","57cb2404cc8e0d025ab9ce7d","57c8e83210b51d256eec3930","57c8e85310b51d256eec3932","57c8e89e10b51d256eec3934","57c8e8ab10b51d256eec3935","57c8e8c010b51d256eec3936","57c8e8d210b51d256eec3938","57c8e8f210b51d256eec393a","57c8e8fe10b51d256eec393b","57c8e90a10b51d256eec393c","57c8e91610b51d256eec393d","57c8e92410b51d256eec393e","57c8e93710b51d256eec393f"],"cloudRecentUsedOrder":{"57c8ef1110b51d256eec3981":1662127162518,"61838cb685b89966c0bf3b49":1663576983015,"61838cb885b89966c0bf54f4":1663576992120,"57cb358ccc8e0d025ab9cee7":1667662558442,"61838cbb85b89966c0bf7800":1667891398526,"61838caf85b89966c0beff14":1667891401496,"61838cc185b89966c0bfba30":1667891402682,"61838cbf85b89966c0bfab04":1667891403599,"61838cc485b89966c0bfe116":1667891404704,"57cb29c0b57de202953056fb":1667891406022,"57cb19c1cc8e0d025ab9ce06":1667891407554,"58175fd3df4f792e31cfb3f7":1667891408628,"61838cb685b89966c0bf3f58":1667891409491,"61838cc485b89966c0bfe352":1667891412747,"61838cbe85b89966c0bf9811":1667891413923,"61838cb785b89966c0bf4343":1667891414805,"61838caf85b89966c0beff93":1667891415783,"57cb1b7cb57de20295305663":1677682302333,"61838cb385b89966c0bf1da7":1677682309619,"61838cbe85b89966c0bf9b61":1677682332057,"5816ef98df4f792e31cfb043":1677682334574,"61838cbf85b89966c0bfa87d":1685329295543,"61838cb785b89966c0bf419e":1685465811579,"61838cc385b89966c0bfd252":1685465849888,"61838cb785b89966c0bf46d7":1685465886335,"61838cbb85b89966c0bf7b53":1698113759348,"61838cba85b89966c0bf694e":1698113806172,"61838cc785b89966c0c00449":1698113808973,"61838cc585b89966c0bff652":1698113809988,"57caf0cdb57de202953054ad":1701766866714,"678539afd0a997bae4c97f7b":1736870999885,"67868b2f21aea7bafd11109e":1736992133662,"6787dcaf21aea7bafd11134f":1737088088291,"67892e2f99ae35badee76713":1737176606422,"678a7fb0d0a997bae4c989ed":1737259502990,"678bd12fd0a997bae4c98b9b":1737382145143,"678d22afd0a997bae4c98d27":1737427803448,"678e742f99ae35badee76f00":1737524703250,"678fc5b0d0a997bae4c991ee":1737598066648,"6791172f2ab932baf64f979c":1737731636888,"679268af21aea7bafd1124f5":1737820020939,"6793ba2f21aea7bafd112751":1737824414494,"67950baf99ae35badee778e9":1737907513485,"67965d2f21aea7bafd1129f5":1738059011697,"6797aeaf2ab932baf64f9fce":1738081265311,"6799002f21aea7bafd112c57":1738166719548,"679a51b021aea7bafd112d8c":1738386233293,"679cf4af2ab932baf64fa3a9":1738489426156,"679e462f99ae35badee7823b":1738517515526,"679f97af21aea7bafd1132c7":1738676949757,"67a0e92f21aea7bafd1135cc":1738739308402,"67a23aafd0a997bae4c9a928":1738772121881,"67a38c2f2ab932baf64faefe":1738900771661,"67a4ddafd0a997bae4c9adfc":1738945513633,"67a62f2fd0a997bae4c9b12b":1739031088661,"67a780af99ae35badee792b1":1739153767379,"67a8d22f99ae35badee7942c":1739249598820,"67aa23af21aea7bafd11473e":1739329246747,"67ab752f2ab932baf64fbe43":1739449556389,"67acc6af21aea7bafd114cff":1739500167639,"67ae182f99ae35badee79ff8":1739587469081,"67af69af21aea7bafd11532a":1739637205007,"61838cba85b89966c0bf68dd":1739629254534,"67b0bb2fd0a997bae4c9c52c":1739724155789,"67b20caf99ae35badee7a67c":1739976377105,"67b4afaf99ae35badee7ad01":1739983821843,"67b6012f99ae35badee7b0fd":1740076349464,"67b8a42f99ae35badee7bb15":1740241972848,"67b9f5af21aea7bafd116ecd":1740327773580,"67bb472f2ab932baf64fe333":1740454753784,"67bc98af99ae35badee7c2cf":1740541958313,"67bdea2f99ae35badee7c62a":1740585971852,"67bf3baf2ab932baf64fefda":1740706520878,"67c08d2fd0a997bae4c9f221":1740792566184,"67c1deaf99ae35badee7d486":1740886012029,"67c3302f99ae35badee7d67c":1740974968817,"67c481af99ae35badee7d825":1741076205971,"67c5d58821aea7bafd119018":1741138562941,"67c724af99ae35badee7e75e":1741227094387,"67c8762f21aea7bafd119c11":1741282467083,"67c9c7af99ae35badee7ee30":1741399643716,"67cb192f99ae35badee7f139":1741484422412,"67cc6aafd0a997bae4ca13c1":1741582087881,"67cdbc2fd0a997bae4ca15ad":1741655994146,"67cf0dafd0a997bae4ca18c5":1741745658260,"67d05f2f99ae35badee7fb1e":1741830853652,"67d1b0afd0a997bae4ca214d":1741830853778,"57cb2404cc8e0d025ab9ce7d":1761638596942,"57c8e83210b51d256eec3930":1761750794984,"57c8e85310b51d256eec3932":1761914061390,"57c8e89e10b51d256eec3934":1762003617960,"57c8e8ab10b51d256eec3935":1762066546346,"57c8e8c010b51d256eec3936":1762241788020,"57c8e8d210b51d256eec3938":1762521869391,"57c8e8f210b51d256eec393a":1763049583671,"57c8e8fe10b51d256eec393b":1763651796953,"57c8e90a10b51d256eec393c":1763714809275,"57c8e91610b51d256eec393d":1763779943284,"57c8e92410b51d256eec393e":1764150912355,"57c8e93710b51d256eec393f":1764693066977},"customColorItems":[],"nextPage":0,"totalPage":-1,"wpExt":"png"},"searcher":{"searchEngine":{"custom":[],"addList":[],"current":{"name":"谷歌","uuid":"a22dcc25c75de3f58cb518e32c576865","logo":"https://infinity-permanent.infinitynewtab.com/infinity/search-add/google.png","desc":"Google搜索是由Google公司推出的一个互联网搜索引擎，它是互联网上最大、影响最广泛的搜索引擎","types":[{"name":"网页","url":"https://www.google.com/search?q="},{"name":"图片","url":"https://www.google.com/search?tbm=isch&q="},{"name":"新闻","url":"https://www.google.com/search?tbm=nws&q="},{"name":"视频","url":"https://www.google.com/search?tbm=vid&q="},{"name":"地图","url":"https://www.google.com/maps/preview?q="}],"hide":true},"all":[{"name":"百度","uuid":"0c47016a8cd2d631bc618d4f3a741335","logo":"https://infinity-permanent.infinitynewtab.com/infinity/search-add/baidu.png","desc":"中国人用的最多的搜索引擎","types":[{"name":"网页","url":"https://www.baidu.com/s?tn=75144485_8_dg&ie=utf-8&wd="},{"name":"图片","url":"https://image.baidu.com/search/index?tn=baiduimage&ie=utf-8&word="},{"name":"新闻","url":"https://news.baidu.com/ns?tn=news&ie=utf-8&word="},{"name":"视频","url":"http://video.baidu.com/v?ie=utf-8&word="},{"name":"地图","url":"http://map.baidu.com/?newmap=1&ie=utf-8&s=s%26wd%3D"}]},{"name":"谷歌","uuid":"a22dcc25c75de3f58cb518e32c576865","logo":"https://infinity-permanent.infinitynewtab.com/infinity/search-add/google.png","desc":"Google搜索是由Google公司推出的一个互联网搜索引擎，它是互联网上最大、影响最广泛的搜索引擎","types":[{"name":"网页","url":"https://www.google.com/search?q="},{"name":"图片","url":"https://www.google.com/search?tbm=isch&q="},{"name":"新闻","url":"https://www.google.com/search?tbm=nws&q="},{"name":"视频","url":"https://www.google.com/search?tbm=vid&q="},{"name":"地图","url":"https://www.google.com/maps/preview?q="}],"hide":true},{"name":"必应","uuid":"5a6afaa65c95a841f6149c4e1591a637","logo":"https://infinity-permanent.infinitynewtab.com/infinity/search-add/bing_new.png","desc":"必应是一款由微软公司推出的网络搜索引擎","types":[{"name":"网页","url":"https://cn.bing.com/search?form=bing&q="},{"name":"图片","url":"https://cn.bing.com/images/search?q="},{"name":"视频","url":"https://cn.bing.com/videos/search?q="},{"name":"地图","url":"https://cn.bing.com/maps?q="}]},{"name":"雅虎","uuid":"C26068F55492EF9E93E05E34A3B31139","logo":"https://infinity-permanent.infinitynewtab.com/infinity/search-add/yahoo.png","desc":"雅虎搜索是一个由Yahoo!运营的互联网搜索引擎","types":[{"name":"网页","url":"https://infinitysearch.io/yahoofind?q="},{"name":"图片","url":"https://images.search.yahoo.com/search/images?p="},{"name":"新闻","url":"https://news.search.yahoo.com/search?p="},{"name":"视频","url":"https://video.search.yahoo.com/search/video?p="}]}]}},"todo":{"todoList":[]},"note":{"list":[{"content":"","id":"95b6ae19-5ee9-4f2e-932e-6b928da55cf6","time":1587702077795,"title":"","updatetime":1623332116995,"fontSize":14}],"checkedId":"95b6ae19-5ee9-4f2e-932e-6b928da55cf6"},"weather":{"list":[{"cid":"CN101180112","updateTime":1764664440000,"updateIntervalMills":28800000,"items":[{"time":1764633600000,"conditionCode":"100","tmpMin":"-1","tmpMax":"6","windScale":"1-3","humidity":"29","pressure":"1019"},{"time":1764720000000,"conditionCode":"100","tmpMin":"-1","tmpMax":"10","windScale":"1-3","humidity":"38","pressure":"1011"},{"time":1764806400000,"conditionCode":"101","tmpMin":"-1","tmpMax":"13","windScale":"1-3","humidity":"38","pressure":"1017"},{"time":1764892800000,"conditionCode":"100","tmpMin":"0","tmpMax":"10","windScale":"1-3","humidity":"40","pressure":"1005"},{"time":1764979200000,"conditionCode":"101","tmpMin":"4","tmpMax":"18","windScale":"1-3","humidity":"33","pressure":"1006"},{"time":1765065600000,"conditionCode":"104","tmpMin":"2","tmpMax":"15","windScale":"1-3","humidity":"34","pressure":"1015"},{"time":1765152000000,"conditionCode":"104","tmpMin":"1","tmpMax":"12","windScale":"1-3","humidity":"31","pressure":"1019"}],"name":"金水"}],"unit":"celsius"}}}